Workbook

Sheet Cover
B7: ASHWORTH & KENSINGTON
B9: H O L D I N G S P L C
B14: Integrated Financial Model • Valuation • Econometric Analysis
B16: Fiscal Years 2021A – 2030E
F19: ❦
C27: C O N T E N T S
D29: 1. | E29: How to Use This Model (README)
D30: 2. | E30: Executive Dashboard
D31: 3. | E31: Scenario Analysis
D32: 4. | E32: Key Assumptions & Drivers
D33: 5. | E33: Revenue Build (by Segment)
D34: 6. | E34: Income Statement
D35: 7. | E35: Working Capital Schedule
D36: 8. | E36: Debt Schedule
D37: 9. | E37: Balance Sheet
D38: 10. | E38: Cash Flow Statement
D39: 11. | E39: DCF Valuation
D40: 12. | E40: Comparable Company Valuation
... D43: 15. | E43: Model Integrity Checks
B46: EDUCATIONAL FINANCIAL MODELING PROJECT — PREPARED BY DEEPIKA KUMARI

Sheet README
B1: HOW TO USE THIS MODEL
B6: Ashworth & Kensington Holdings plc — Integrated Financial Model
B8: Version: | C8: v1.0
B9: Last Updated: | C9: July 2026
B10: Author: | C10: Deepika Kumari
B11: Purpose: | C11: Educational Portfolio Project
B13: 1. Overview
B14: This workbook is a fully-linked, three-statement financial model for a fictional holding company with three segments (Heritage Textiles, Private Wealth Advisory, Fine Estates). It builds a bottom-up revenue forecast, rolls it through the Income Statement, Balance Sheet, and Cash Flow Statement, and produces two independent valuations — a Discounted Cash Flow and a Comparable Company analysis — which are reconciled in a single valuation range. Every number in the model is either a hard-coded input, a formula, or a link to another sheet; nothing is pasted as a static value.
B19: 2. Color Conventions (used consistently on every sheet)
B20: ■ Blue text | C20: A hard-coded input you can safely change — historical actuals, assumptions, or scenario values.
B21: ■ Black text | C21: A formula. Do not overwrite — it calculates automatically from other cells.
B22: ■ Green text | C22: A link that pulls a value from another sheet, so you can trace where a number came from.
B23: ■ Gold fill | C23: A key output, subtotal, or the “selected” scenario value — the number you most want to look at on that sheet.
B25: 3. How the Model Flows
B26: ▸ Scenarios | C26: Choose Bear / Base / Bull from the dropdown — this is the master switch for the entire model.
B27: ▸ Assumptions | C27: Macro, margin, and capital-structure drivers. Scenario adjustments are layered on here.
B28: ▸ Revenue Build | C28: Units Sold × Average Selling Price, by segment, rolls up to Total Revenue.
B29: ▸ Income Statement | C29: Revenue flows down to Net Income using the margin assumptions and Debt Schedule interest.
B30: ▸ Working Capital / Debt Schedule | C30: Supporting schedules for AR/Inventory/AP (DSO/DIO/DPO) and the debt roll-forward.
B31: ▸ Balance Sheet / Cash Flow | C31: Fully articulated and mechanically balanced — see the Checks tab.
B32: ▸ DCF Valuation / Comparables | C32: Two independent valuations, reconciled on the Comparables tab's valuation range.
B33: ▸ Sensitivity / Econometrics | C33: WACC × growth data table, CAPM beta regression, and macro regressions.
B34: ▸ Checks | C34: Ten automated integrity tests — everything should read ✅ PASS.
B36: 4. Running a Scenario
B37: Go to the Scenarios tab → click the dropdown in cell C6 → choose Bear, Base, or Bull. Every projected assumption (volume growth, pricing, margins, WACC, terminal growth) updates immediately via CHOOSE() / INDEX() / MATCH() formulas, and the change flows all the way through to the Dashboard KPIs, the DCF implied share price, and the Comparables valuation range.
B41: 5. Named Ranges (Name Box or Ctrl+G to jump)
B42: Scenario_Selector | C42: The Bear/Base/Bull dropdown cell
B43: WACC | C43: Scenario-adjusted discount rate
B44: Terminal_Growth_Rate | C44: Scenario-adjusted terminal growth rate
B45: Implied_Share_Price_DCF | C45: DCF Valuation tab's headline output
B46: Implied_Valuation_Range_Low | C46: Low end of the all-methods valuation range
B47: Implied_Valuation_Range_High | C47: High end of the all-methods valuation range
B49: 6. Notes & Disclaimer
B50: Ashworth & Kensington Holdings plc is a fictional company created for illustrative and educational purposes. All figures, comparable companies, and multiples are invented and should not be used for any real investment decision. This workbook is intended to demonstrate financial modeling and econometric technique in Excel.

Sheet Dashboard
B1: EXECUTIVE DASHBOARD
B3: ■ Blue = Input ■ Black = Formula ■ Green = Link to Another Sheet
B6: Ashworth & Kensington Holdings plc — FY2030E Snapshot
B8: Total Revenue (FY30E) | F8: EBITDA (FY30E) | J8: Net Income (FY30E) | N8: Diluted EPS (FY30E) | R8: Implied Share Price
B9: ='Income Statement'!L6 -> 491199.41 | F9: ='Income Statement'!L12 -> 140483.03 | J9: ='Income Statement'!L22 -> 92298.011 | N9: ='Income Statement'!L26 -> 1.9030518 | R9: ='DCF Valuation'!C28 -> 25.247626
B11: '25–'30 CAGR: | F11: EBITDA Margin: | J11: Net Margin: | N11: WACC: | R11: Beta:
B12: =(('Income Statement'!L6/'Income Statement'!G6)^(1/5))-1 -> 0.055530973 | F12: ='Income Statement'!L12/'Income Statement'!L6 -> 0.286 | J12: ='Income Statement'!L22/'Income Statement'!L6 -> 0.18790334 | N12: =Assumptions!$C$40 -> 0.099535182 | R12: =Assumptions!$C$35 -> 1.3085269
B39: (chart data — linked)
C40: 2021 | D40: 2022 | E40: 2023 | F40: 2024 | G40: 2025 | H40: 2026 | I40: 2027 | J40: 2028 | K40: 2029 | L40: 2030
B41: Revenue | C41: ='Income Statement'!C6 -> 269300.04 | D41: ='Income Statement'!D6 -> 289614.82 | E41: ='Income Statement'!E6 -> 317950.41 | F41: ='Income Statement'!F6 -> 344406.1 | G41: ='Income Statement'!G6 -> 374889.2 | H41: ='Income Statement'!H6 -> 398117.3 | I41: ='Income Statement'!I6 -> 421513.74 | J41: ='Income Statement'!J6 -> 444882.39 | ... L41: ='Income Statement'!L6 -> 491199.41
B42: Revenue (Historical) | C42: ='Income Statement'!C6 -> 269300.04 | D42: ='Income Statement'!D6 -> 289614.82 | E42: ='Income Statement'!E6 -> 317950.41 | F42: ='Income Statement'!F6 -> 344406.1 | G42: ='Income Statement'!G6 -> 374889.2
B43: Revenue (Forecast) | H43: ='Income Statement'!H6 -> 398117.3 | I43: ='Income Statement'!I6 -> 421513.74 | J43: ='Income Statement'!J6 -> 444882.39 | K43: ='Income Statement'!K6 -> 468182.39 | L43: ='Income Statement'!L6 -> 491199.41
B44: EBITDA | C44: ='Income Statement'!C12 -> 59246.009 | D44: ='Income Statement'!D12 -> 66611.409 | E44: ='Income Statement'!E12 -> 76308.098 | F44: ='Income Statement'!F12 -> 86101.525 | G44: ='Income Statement'!G12 -> 97471.192 | H44: ='Income Statement'!H12 -> 105899.2 | I44: ='Income Statement'!I12 -> 114651.74 | J44: ='Income Statement'!J12 -> 123677.3 | ... L44: ='Income Statement'!L12 -> 140483.03
B45: EBITDA Margin % | C45: ='Income Statement'!C12/'Income Statement'!C6 -> 0.22 | D45: ='Income Statement'!D12/'Income Statement'!D6 -> 0.23 | E45: ='Income Statement'!E12/'Income Statement'!E6 -> 0.24 | F45: ='Income Statement'!F12/'Income Statement'!F6 -> 0.25 | G45: ='Income Statement'!G12/'Income Statement'!G6 -> 0.26 | H45: ='Income Statement'!H12/'Income Statement'!H6 -> 0.266 | I45: ='Income Statement'!I12/'Income Statement'!I6 -> 0.272 | J45: ='Income Statement'!J12/'Income Statement'!J6 -> 0.278 | ... L45: ='Income Statement'!L12/'Income Statement'!L6 -> 0.286
B46: Net Income | C46: ='Income Statement'!C22 -> 33530.515 | D46: ='Income Statement'!D22 -> 38752.241 | E46: ='Income Statement'!E22 -> 45389.857 | F46: ='Income Statement'!F22 -> 52543.874 | G46: ='Income Statement'!G22 -> 60506.386 | H46: ='Income Statement'!H22 -> 66641.569 | I46: ='Income Statement'!I22 -> 73035.873 | J46: ='Income Statement'!J22 -> 79966.38 | ... L46: ='Income Statement'!L22 -> 92298.011
B47: Cash Flow from Operations | D47: ='Cash Flow'!D12 -> 47791.028 | E47: ='Cash Flow'!E12 -> 54316.327 | F47: ='Cash Flow'!F12 -> 62351.714 | G47: ='Cash Flow'!G12 -> 70621.661 | H47: ='Cash Flow'!H12 -> 78394.139 | I47: ='Cash Flow'!I12 -> 85194.457 | J47: ='Cash Flow'!J12 -> 92950.199 | K47: ='Cash Flow'!K12 -> 99586.52 | L47: ='Cash Flow'!L12 -> 106444.14
B48: Revenue Growth % | D48: ='Revenue Build'!D23 -> 0.075435488 | E48: ='Revenue Build'!E23 -> 0.097838881 | F48: ='Revenue Build'!F23 -> 0.083206969 | G48: ='Revenue Build'!G23 -> 0.088509176 | H48: ='Revenue Build'!H23 -> 0.061959909 | I48: ='Revenue Build'!I23 -> 0.058767701 | J48: ='Revenue Build'!J23 -> 0.05543983 | K48: ='Revenue Build'!K23 -> 0.05237339 | L48: ='Revenue Build'!L23 -> 0.049162512
B49: Unlevered Free Cash Flow | H49: ='DCF Valuation'!H13 -> 66553.416 | I49: ='DCF Valuation'!I13 -> 72829.164 | J49: ='DCF Valuation'!J13 -> 79573.815 | K49: ='DCF Valuation'!K13 -> 85653.819 | L49: ='DCF Valuation'!L13 -> 91519.862
B50: Segment Mix FY30E
B51: Heritage Textiles | C51: ='Revenue Build'!L9 -> 177056.46
B52: Private Wealth Advisory | C52: ='Revenue Build'!L14 -> 216475.03
B53: Fine Estates | C53: ='Revenue Build'!L19 -> 97667.921
B55: DCF Bridge | C55: PV of FCF ('26-'30) | D55: PV of Terminal Value | E55: Enterprise Value | F55: Net Debt / (Net Cash) | G55: Equity Value
B56: base | C56: =0 -> 0 | D56: ='DCF Valuation'!C21*0+'DCF Valuation'!C19 -> 296178.36 | E56: =0 -> 0 | F56: ='DCF Valuation'!C26 -> 1224509.9 | G56: =0 -> 0
B57: value | C57: ='DCF Valuation'!C19 -> 296178.36 | D57: ='DCF Valuation'!C21 -> 761174.49 | E57: ='DCF Valuation'!C22 -> 1057352.8 | F57: ='DCF Valuation'!C25 -> -167157.03 | G57: ='DCF Valuation'!C26 -> 1224509.9
B93: Tornado — Share Price Sensitivity to Key Drivers
B94: Driver | C94: Low | D94: High | E94: Swing
B95: WACC ± 50 bps | C95: =Sensitivity!F12 -> 23.873143 | D95: =Sensitivity!F10 -> 26.814999 | E95: =D95-C95 -> 2.9418565
B96: Terminal Growth ± 50 bps | C96: =Sensitivity!E11 -> 24.213197 | D96: =Sensitivity!G11 -> 26.42666 | E96: =D96-C96 -> 2.2134635
B97: Exit Multiple ± 1.0x | C97: =Comparables!C39 -> 28.477867 | D97: =Comparables!D39 -> 32.082545 | E97: =D97-C97 -> 3.604678
B98: FY26-30E Revenue ± 5% (illustrative) | C98: =(('DCF Valuation'!H13*0.95/(1+Assumptions!$C$40)^1+'DCF Valuation'!I13*0.95/(1+Assumptions!$C$40)^2+'DCF Valuation'!J13*0.95/(1+Assumptions!$C$40)^3+'DCF Valuation'!K13*0.95/(1+Assumptions!$C$40)^4+'DCF Valuation'!L13*0.95/(1+Assumptions!$C$40)^5)+(('DCF Valuation'!L13*0.95*(1+Assumptions!$C$41))/(Assumptions!$C$40-Assumptions!$C$41)/(1+Assumptions!$C$40)^5)-'DCF Valuation'!C25)/(Assumptions!$C$42*1000) -> 24.157572 | D98: =(('DCF Valuation'!H13*1.05/(1+Assumptions!$C$40)^1+'DCF Valuation'!I13*1.05/(1+Assumptions!$C$40)^2+'DCF Valuation'!J13*1.05/(1+Assumptions!$C$40)^3+'DCF Valuation'!K13*1.05/(1+Assumptions!$C$40)^4+'DCF Valuation'!L13*1.05/(1+Assumptions!$C$40)^5)+(('DCF Valuation'!L13*1.05*(1+Assumptions!$C$41))/(Assumptions!$C$40-Assumptions!$C$41)/(1+Assumptions!$C$40)^5)-'DCF Valuation'!C25)/(Assumptions!$C$42*1000) -> 26.337681 | E98: =D98-C98 -> 2.180109

Sheet Scenarios
B1: SCENARIO ANALYSIS
B3: ■ Blue = Input ■ Black = Formula ■ Green = Link to Another Sheet
B6: Active Scenario | C6: Base
B7: Scenario Index (1 = Bear, 2 = Base, 3 = Bull) | C7: =MATCH(C6,{"Bear","Base","Bull"},0) -> 2
B9: Narrative
B10: Bear: recessionary volume pullback, pricing pressure, wider discount rate. Base: steady-state continuation of current trends. Bull: accelerating client wins, pricing power, and margin expansion.
B12: Adjustment vs. Base Case (percentage points) | C12: BEAR | D12: BASE | E12: BULL | F12: SELECTED ►
B13: Heritage Textiles — Units Growth Adj. | C13: -0.015 | D13: 0 | E13: 0.015 | F13: =CHOOSE(Scenarios!$C$7,C13,D13,E13) -> 0
B14: Private Wealth — Client Growth Adj. | C14: -0.025 | D14: 0 | E14: 0.025 | F14: =CHOOSE(Scenarios!$C$7,C14,D14,E14) -> 0
B15: Fine Estates — Transaction Growth Adj. | C15: -0.02 | D15: 0 | E15: 0.02 | F15: =CHOOSE(Scenarios!$C$7,C15,D15,E15) -> 0
B16: Heritage Textiles — ASP Growth Adj. | C16: -0.006 | D16: 0 | E16: 0.006 | F16: =CHOOSE(Scenarios!$C$7,C16,D16,E16) -> 0
B17: Private Wealth — Fee/Account Growth Adj. | C17: -0.005 | D17: 0 | E17: 0.005 | F17: =CHOOSE(Scenarios!$C$7,C17,D17,E17) -> 0
B18: Fine Estates — Avg. Fee Growth Adj. | C18: -0.005 | D18: 0 | E18: 0.005 | F18: =CHOOSE(Scenarios!$C$7,C18,D18,E18) -> 0
B19: Gross Margin Adj. | C19: -0.012 | D19: 0 | E19: 0.01 | F19: =CHOOSE(Scenarios!$C$7,C19,D19,E19) -> 0
B20: SG&A % Adj. (+ = higher cost) | C20: 0.01 | D20: 0 | E20: -0.008 | F20: =CHOOSE(Scenarios!$C$7,C20,D20,E20) -> 0
B21: Terminal Growth Rate Adj. | C21: -0.005 | D21: 0 | E21: 0.004 | F21: =INDEX(C21:E21,1,MATCH(Scenarios!$C$6,{"Bear","Base","Bull"},0)) -> 0
B22: WACC Adj. (+ = higher discount rate) | C22: 0.006 | D22: 0 | E22: -0.005 | F22: =INDEX(C22:E22,1,MATCH(Scenarios!$C$6,{"Bear","Base","Bull"},0)) -> 0

Sheet Assumptions
B1: KEY ASSUMPTIONS & DRIVERS
C3: ACTUAL | H3: PROJECTED
B4: ($ in 000s, unless noted) | C4: 2021 | D4: 2022 | E4: 2023 | F4: 2024 | G4: 2025 | H4: 2026 | I4: 2027 | J4: 2028 | K4: 2029 | L4: 2030
B5: ■ Blue = Input ■ Black = Formula ■ Green = Link to Another Sheet
B6: Macroeconomic Environment
B7: Real GDP Growth (%) | C7: 0.031 | D7: 0.021 | E7: 0.025 | F7: 0.028 | G7: 0.023 | H7: 0.021 | I7: 0.02 | J7: 0.02 | K7: 0.019 | L7: 0.019
B8: CPI Inflation (%) | C8: 0.047 | D8: 0.08 | E8: 0.041 | F8: 0.03 | G8: 0.026 | H8: 0.024 | I8: 0.022 | J8: 0.021 | K8: 0.02 | L8: 0.02
B9: 10-Year Treasury Yield / Risk-Free Rate (%) | C9: 0.015 | D9: 0.039 | E9: 0.04 | F9: 0.043 | G9: 0.044 | H9: 0.042 | I9: 0.04 | J9: 0.039 | K9: 0.038 | L9: 0.038
B11: Segment Volume & Pricing Assumptions
B12: Heritage Textiles — Units Growth (%) | D12: =IFERROR('Revenue Build'!D7/'Revenue Build'!C7-1,"") -> 0.014018692 | E12: =IFERROR('Revenue Build'!E7/'Revenue Build'!D7-1,"") -> 0.016129032 | F12: =IFERROR('Revenue Build'!F7/'Revenue Build'!E7-1,"") -> 0.0090702948 | G12: =IFERROR('Revenue Build'!G7/'Revenue Build'!F7-1,"") -> 0.013483146 | H12: =0.01+Scenarios!$F$13 -> 0.01 | I12: =0.01+Scenarios!$F$13 -> 0.01 | J12: =0.009+Scenarios!$F$13 -> 0.009 | K12: =0.009+Scenarios!$F$13 -> 0.009 | L12: =0.008+Scenarios!$F$13 -> 0.008
B13: Heritage Textiles — ASP Growth (%) | D13: =IFERROR('Revenue Build'!D8/'Revenue Build'!C8-1,"") -> 0.030833333 | E13: =IFERROR('Revenue Build'!E8/'Revenue Build'!D8-1,"") -> 0.037186742 | F13: =IFERROR('Revenue Build'!F8/'Revenue Build'!E8-1,"") -> 0.02852689 | G13: =IFERROR('Revenue Build'!G8/'Revenue Build'!F8-1,"") -> 0.027584116 | H13: =0.023+Scenarios!$F$16 -> 0.023 | I13: =0.021+Scenarios!$F$16 -> 0.021 | J13: =0.02+Scenarios!$F$16 -> 0.02 | K13: =0.019+Scenarios!$F$16 -> 0.019 | L13: =0.019+Scenarios!$F$16 -> 0.019
B14: Private Wealth Advisory — Client Growth (%) | D14: =IFERROR('Revenue Build'!D12/'Revenue Build'!C12-1,"") -> 0.094117647 | E14: =IFERROR('Revenue Build'!E12/'Revenue Build'!D12-1,"") -> 0.10752688 | F14: =IFERROR('Revenue Build'!F12/'Revenue Build'!E12-1,"") -> 0.10679612 | G14: =IFERROR('Revenue Build'!G12/'Revenue Build'!F12-1,"") -> 0.096491228 | H14: =0.065+Scenarios!$F$14 -> 0.065 | I14: =0.06+Scenarios!$F$14 -> 0.06 | J14: =0.055+Scenarios!$F$14 -> 0.055 | K14: =0.05+Scenarios!$F$14 -> 0.05 | L14: =0.045+Scenarios!$F$14 -> 0.045
B15: Private Wealth Advisory — Fee/Account Growth (%) | D15: =IFERROR('Revenue Build'!D13/'Revenue Build'!C13-1,"") -> 0.03167278 | E15: =IFERROR('Revenue Build'!E13/'Revenue Build'!D13-1,"") -> 0.044884539 | F15: =IFERROR('Revenue Build'!F13/'Revenue Build'!E13-1,"") -> 0.030296378 | G15: =IFERROR('Revenue Build'!G13/'Revenue Build'!F13-1,"") -> 0.034874636 | H15: =0.028+Scenarios!$F$17 -> 0.028 | I15: =0.027+Scenarios!$F$17 -> 0.027 | J15: =0.026+Scenarios!$F$17 -> 0.026 | K15: =0.025+Scenarios!$F$17 -> 0.025 | L15: =0.024+Scenarios!$F$17 -> 0.024
B16: Fine Estates — Transaction Growth (%) | D16: =IFERROR('Revenue Build'!D17/'Revenue Build'!C17-1,"") -> 0.025641026 | E16: =IFERROR('Revenue Build'!E17/'Revenue Build'!D17-1,"") -> 0.05 | F16: =IFERROR('Revenue Build'!F17/'Revenue Build'!E17-1,"") -> 0.047619048 | G16: =IFERROR('Revenue Build'!G17/'Revenue Build'!F17-1,"") -> 0.045454545 | H16: =0.03+Scenarios!$F$15 -> 0.03 | I16: =0.028+Scenarios!$F$15 -> 0.028 | J16: =0.026+Scenarios!$F$15 -> 0.026 | K16: =0.024+Scenarios!$F$15 -> 0.024 | L16: =0.022+Scenarios!$F$15 -> 0.022
B17: Fine Estates — Avg. Fee Growth (%) | D17: =IFERROR('Revenue Build'!D18/'Revenue Build'!C18-1,"") -> 0.03560632 | E17: =IFERROR('Revenue Build'!E18/'Revenue Build'!D18-1,"") -> 0.04745611 | F17: =IFERROR('Revenue Build'!F18/'Revenue Build'!E18-1,"") -> 0.033718278 | G17: =IFERROR('Revenue Build'!G18/'Revenue Build'!F18-1,"") -> 0.054662911 | H17: =0.026+Scenarios!$F$18 -> 0.026 | I17: =0.025+Scenarios!$F$18 -> 0.025 | J17: =0.024+Scenarios!$F$18 -> 0.024 | K17: =0.023+Scenarios!$F$18 -> 0.023 | L17: =0.022+Scenarios!$F$18 -> 0.022
B19: Blended Segment Revenue Growth (Derived, Units × ASP)
B20: Heritage Textiles — Total Revenue Growth (%) | D20: =IFERROR('Revenue Build'!D9/'Revenue Build'!C9-1,"") -> 0.045284268 | E20: =IFERROR('Revenue Build'!E9/'Revenue Build'!D9-1,"") -> 0.053915561 | F20: =IFERROR('Revenue Build'!F9/'Revenue Build'!E9-1,"") -> 0.037855932 | G20: =IFERROR('Revenue Build'!G9/'Revenue Build'!F9-1,"") -> 0.041439183 | H20: =IFERROR('Revenue Build'!H9/'Revenue Build'!G9-1,"") -> 0.03323 | I20: =IFERROR('Revenue Build'!I9/'Revenue Build'!H9-1,"") -> 0.03121 | J20: =IFERROR('Revenue Build'!J9/'Revenue Build'!I9-1,"") -> 0.02918 | K20: =IFERROR('Revenue Build'!K9/'Revenue Build'!J9-1,"") -> 0.028171 | L20: =IFERROR('Revenue Build'!L9/'Revenue Build'!K9-1,"") -> 0.027152
B21: Private Wealth Advisory — Total Revenue Growth (%) | D21: =IFERROR('Revenue Build'!D14/'Revenue Build'!C14-1,"") -> 0.12877139 | E21: =IFERROR('Revenue Build'!E14/'Revenue Build'!D14-1,"") -> 0.15723772 | F21: =IFERROR('Revenue Build'!F14/'Revenue Build'!E14-1,"") -> 0.14032803 | G21: =IFERROR('Revenue Build'!G14/'Revenue Build'!F14-1,"") -> 0.13473096 | H21: =IFERROR('Revenue Build'!H14/'Revenue Build'!G14-1,"") -> 0.09482 | I21: =IFERROR('Revenue Build'!I14/'Revenue Build'!H14-1,"") -> 0.08862 | J21: =IFERROR('Revenue Build'!J14/'Revenue Build'!I14-1,"") -> 0.08243 | K21: =IFERROR('Revenue Build'!K14/'Revenue Build'!J14-1,"") -> 0.07625 | L21: =IFERROR('Revenue Build'!L14/'Revenue Build'!K14-1,"") -> 0.07008
B22: Fine Estates (Real Assets) — Total Revenue Growth (%) | D22: =IFERROR('Revenue Build'!D19/'Revenue Build'!C19-1,"") -> 0.062160328 | E22: =IFERROR('Revenue Build'!E19/'Revenue Build'!D19-1,"") -> 0.099828916 | F22: =IFERROR('Revenue Build'!F19/'Revenue Build'!E19-1,"") -> 0.082942958 | G22: =IFERROR('Revenue Build'!G19/'Revenue Build'!F19-1,"") -> 0.10260213 | H22: =IFERROR('Revenue Build'!H19/'Revenue Build'!G19-1,"") -> 0.05678 | I22: =IFERROR('Revenue Build'!I19/'Revenue Build'!H19-1,"") -> 0.0537 | J22: =IFERROR('Revenue Build'!J19/'Revenue Build'!I19-1,"") -> 0.050624 | K22: =IFERROR('Revenue Build'!K19/'Revenue Build'!J19-1,"") -> 0.047552 | L22: =IFERROR('Revenue Build'!L19/'Revenue Build'!K19-1,"") -> 0.044484
B24: Margin & Cost Assumptions
B25: Gross Margin (%) | C25: 0.56 | D25: 0.565 | E25: 0.57 | F25: 0.575 | G25: 0.58 | H25: =0.583+Scenarios!$F$19 -> 0.583 | I25: =0.586+Scenarios!$F$19 -> 0.586 | J25: =0.589+Scenarios!$F$19 -> 0.589 | K25: =0.591+Scenarios!$F$19 -> 0.591 | L25: =0.593+Scenarios!$F$19 -> 0.593
B26: SG&A (% of Revenue) | C26: 0.34 | D26: 0.335 | E26: 0.33 | F26: 0.325 | G26: 0.32 | H26: =0.317+Scenarios!$F$20 -> 0.317 | I26: =0.314+Scenarios!$F$20 -> 0.314 | J26: =0.311+Scenarios!$F$20 -> 0.311 | K26: =0.309+Scenarios!$F$20 -> 0.309 | L26: =0.307+Scenarios!$F$20 -> 0.307
B27: D&A (% of Revenue) | C27: 0.04 | D27: 0.039 | E27: 0.038 | F27: 0.037 | G27: 0.036 | H27: 0.036 | I27: 0.035 | J27: 0.035 | K27: 0.034 | L27: 0.034
B28: Effective Tax Rate (%) | C28: 0.26 | D28: 0.255 | E28: 0.255 | F28: 0.25 | G28: 0.25 | H28: 0.245 | I28: 0.245 | J28: 0.24 | K28: 0.24 | L28: 0.24
B29: Capital Expenditures (% of Revenue) | C29: 0.042 | D29: 0.04 | E29: 0.039 | F29: 0.037 | G29: 0.036 | H29: 0.036 | I29: 0.035 | J29: 0.035 | K29: 0.034 | L29: 0.034
B30: Accounts Receivable, Inventory & Payables | C30: see 'Working Capital' tab
B32: Capital Structure & Valuation Assumptions
B33: Risk-Free Rate (Current, 10Y UST) | C33: =Assumptions!H9 -> 0.042
B34: Equity Market Risk Premium | C34: 0.055
B35: Levered Beta (regression-estimated) | C35: =Econometrics!H8 -> 1.3085269
B36: Cost of Equity (CAPM) | C36: =C33+C35*C34 -> 0.11396898
B37: Pre-Tax Cost of Debt | C37: 0.055
B38: After-Tax Cost of Debt | C38: =C37*(1-L28) -> 0.0418
B39: Target Debt / Total Capital | C39: 0.2
B40: WACC (Scenario-Adjusted) | C40: =C36*(1-C39)+C38*C39+Scenarios!$F$22 -> 0.099535182
B41: Terminal Growth Rate (Scenario-Adjusted) | C41: =0.023+Scenarios!$F$21 -> 0.023
B42: Diluted Shares Outstanding (mm) | C42: 48.5
B43: Opening Long-Term Debt, FY2020A ($000s) | C43: 55000 | D43: feeds 'Debt Schedule' tab
B44: Common Stock & APIC ($000s) | C44: 50000

Sheet Revenue Build
B1: REVENUE BUILD — BY SEGMENT
C3: ACTUAL | H3: PROJECTED
B4: ($ in 000s, unless noted) | C4: 2021 | D4: 2022 | E4: 2023 | F4: 2024 | G4: 2025 | H4: 2026 | I4: 2027 | J4: 2028 | K4: 2029 | L4: 2030
B5: ■ Blue = Input ■ Black = Formula ■ Green = Link to Another Sheet
B6: Heritage Textiles — Volume & Pricing
B7: Units Sold (000s of garments) | C7: 2140 | D7: 2170 | E7: 2205 | F7: 2225 | G7: 2255 | H7: =G7*(1+Assumptions!H12) -> 2277.55 | I7: =H7*(1+Assumptions!I12) -> 2300.3255 | J7: =I7*(1+Assumptions!J12) -> 2321.0284 | K7: =J7*(1+Assumptions!K12) -> 2341.9177 | L7: =K7*(1+Assumptions!L12) -> 2360.653
B8: Average Selling Price ($/unit) | C8: 60 | D8: 61.85 | E8: 64.15 | F8: 65.98 | G8: 67.8 | H8: =G8*(1+Assumptions!H13) -> 69.3594 | I8: =H8*(1+Assumptions!I13) -> 70.815947 | J8: =I8*(1+Assumptions!J13) -> 72.232266 | K8: =J8*(1+Assumptions!K13) -> 73.604679 | L8: =K8*(1+Assumptions!L13) -> 75.003168
B9: Revenue ($000s) | C9: =C7*C8 -> 128400 | D9: =D7*D8 -> 134214.5 | E9: =E7*E8 -> 141450.75 | F9: =F7*F8 -> 146805.5 | G9: =G7*G8 -> 152889 | H9: =H7*H8 -> 157969.5 | I9: =I7*I8 -> 162899.73 | J9: =J7*J8 -> 167653.14 | ... L9: =L7*L8 -> 177056.46
B11: Private Wealth Advisory — Volume & Pricing
B12: Client Accounts (000s) | C12: 170 | D12: 186 | E12: 206 | F12: 228 | G12: 250 | H12: =G12*(1+Assumptions!H14) -> 266.25 | I12: =H12*(1+Assumptions!I14) -> 282.225 | J12: =I12*(1+Assumptions!J14) -> 297.74737 | K12: =J12*(1+Assumptions!K14) -> 312.63474 | L12: =K12*(1+Assumptions!L14) -> 326.70331
B13: Average Fee per Account ($) | C13: 507.06 | D13: 523.12 | E13: 546.6 | F13: 563.16 | G13: 582.8 | H13: =G13*(1+Assumptions!H15) -> 599.1184 | I13: =H13*(1+Assumptions!I15) -> 615.2946 | J13: =I13*(1+Assumptions!J15) -> 631.29226 | K13: =J13*(1+Assumptions!K15) -> 647.07456 | L13: =K13*(1+Assumptions!L15) -> 662.60435
B14: Revenue ($000s) | C14: =C12*C13 -> 86200.2 | D14: =D12*D13 -> 97300.32 | E14: =E12*E13 -> 112599.6 | F14: =F12*F13 -> 128400.48 | G14: =G12*G13 -> 145700 | H14: =H12*H13 -> 159515.27 | I14: =I12*I13 -> 173651.52 | J14: =J12*J13 -> 187965.61 | ... L14: =L12*L13 -> 216475.03
B16: Fine Estates (Real Assets) — Volume & Pricing
B17: Transactions / Mandates (#) | C17: 39 | D17: 40 | E17: 42 | F17: 44 | G17: 46 | H17: =G17*(1+Assumptions!H16) -> 47.38 | I17: =H17*(1+Assumptions!I16) -> 48.70664 | J17: =I17*(1+Assumptions!J16) -> 49.973013 | K17: =J17*(1+Assumptions!K16) -> 51.172365 | L17: =K17*(1+Assumptions!L16) -> 52.298157
B18: Average Fee per Transaction ($000s) | C18: 1402.56 | D18: 1452.5 | E18: 1521.43 | F18: 1572.73 | G18: 1658.7 | H18: =G18*(1+Assumptions!H17) -> 1701.8262 | I18: =H18*(1+Assumptions!I17) -> 1744.3719 | J18: =I18*(1+Assumptions!J17) -> 1786.2368 | K18: =J18*(1+Assumptions!K17) -> 1827.3202 | L18: =K18*(1+Assumptions!L17) -> 1867.5213
B19: Revenue ($000s) | C19: =C17*C18 -> 54699.84 | D19: =D17*D18 -> 58100 | E19: =E17*E18 -> 63900.06 | F19: =F17*F18 -> 69200.12 | G19: =G17*G18 -> 76300.2 | H19: =H17*H18 -> 80632.525 | I19: =I17*I18 -> 84962.492 | J19: =J17*J18 -> 89263.633 | ... L19: =L17*L18 -> 97667.921
B21: Consolidated Revenue
B22: Total Revenue | C22: =SUM(C9,C14,C19) -> 269300.04 | D22: =SUM(D9,D14,D19) -> 289614.82 | E22: =SUM(E9,E14,E19) -> 317950.41 | F22: =SUM(F9,F14,F19) -> 344406.1 | G22: =SUM(G9,G14,G19) -> 374889.2 | H22: =SUM(H9,H14,H19) -> 398117.3 | I22: =SUM(I9,I14,I19) -> 421513.74 | J22: =SUM(J9,J14,J19) -> 444882.39 | ... L22: =SUM(L9,L14,L19) -> 491199.41
B23: Total Revenue — YoY Growth (%) | D23: =D22/C22-1 -> 0.075435488 | E23: =E22/D22-1 -> 0.097838881 | F23: =F22/E22-1 -> 0.083206969 | G23: =G22/F22-1 -> 0.088509176 | H23: =H22/G22-1 -> 0.061959909 | I23: =I22/H22-1 -> 0.058767701 | J23: =J22/I22-1 -> 0.05543983 | K23: =K22/J22-1 -> 0.05237339 | L23: =L22/K22-1 -> 0.049162512
B25: Segment Mix (% of Total Revenue)
B26: Heritage Textiles | C26: =C9/C22 -> 0.47679161 | D26: =D9/D22 -> 0.46342414 | E26: =E9/E22 -> 0.44488306 | F26: =F9/F22 -> 0.42625697 | G26: =G9/G22 -> 0.4078245 | H26: =H9/H22 -> 0.39679135 | I26: =I9/I22 -> 0.38646363 | J26: =J9/J22 -> 0.37684824 | ... L26: =L9/L22 -> 0.36045739
B27: Private Wealth Advisory | C27: =C14/C22 -> 0.32008982 | D27: =D14/D22 -> 0.33596458 | E27: =E14/E22 -> 0.35414202 | F27: =F14/F22 -> 0.37281709 | G27: =G14/G22 -> 0.38864817 | H27: =H14/H22 -> 0.40067406 | I27: =I14/I22 -> 0.41197119 | J27: =J14/J22 -> 0.4225063 | ... L27: =L14/L22 -> 0.44070703
B28: Fine Estates (Real Assets) | C28: =C19/C22 -> 0.20311857 | D28: =D19/D22 -> 0.20061128 | E28: =E19/E22 -> 0.20097493 | F28: =F19/F22 -> 0.20092594 | G28: =G19/G22 -> 0.20352734 | H28: =H19/H22 -> 0.20253459 | I28: =I19/I22 -> 0.20156518 | J28: =J19/J22 -> 0.20064546 | ... L28: =L19/L22 -> 0.19883558

Sheet Income Statement
B1: INCOME STATEMENT
C3: ACTUAL | H3: PROJECTED
B4: ($ in 000s, unless noted) | C4: 2021 | D4: 2022 | E4: 2023 | F4: 2024 | G4: 2025 | H4: 2026 | I4: 2027 | J4: 2028 | K4: 2029 | L4: 2030
B5: ■ Blue = Input ■ Black = Formula ■ Green = Link to Another Sheet
B6: Total Revenue | C6: ='Revenue Build'!C22 -> 269300.04 | D6: ='Revenue Build'!D22 -> 289614.82 | E6: ='Revenue Build'!E22 -> 317950.41 | F6: ='Revenue Build'!F22 -> 344406.1 | G6: ='Revenue Build'!G22 -> 374889.2 | H6: ='Revenue Build'!H22 -> 398117.3 | I6: ='Revenue Build'!I22 -> 421513.74 | J6: ='Revenue Build'!J22 -> 444882.39 | ... L6: ='Revenue Build'!L22 -> 491199.41
B7: Cost of Goods Sold | C7: =-C6*(1-Assumptions!C25) -> -118492.02 | D7: =-D6*(1-Assumptions!D25) -> -125982.45 | E7: =-E6*(1-Assumptions!E25) -> -136718.68 | F7: =-F6*(1-Assumptions!F25) -> -146372.59 | G7: =-G6*(1-Assumptions!G25) -> -157453.46 | H7: =-H6*(1-Assumptions!H25) -> -166014.91 | I7: =-I6*(1-Assumptions!I25) -> -174506.69 | J7: =-J6*(1-Assumptions!J25) -> -182846.66 | ... L7: =-L6*(1-Assumptions!L25) -> -199918.16
B8: Gross Profit | C8: =C6+C7 -> 150808.02 | D8: =D6+D7 -> 163632.37 | E8: =E6+E7 -> 181231.73 | F8: =F6+F7 -> 198033.51 | G8: =G6+G7 -> 217435.74 | H8: =H6+H7 -> 232102.39 | I8: =I6+I7 -> 247007.05 | J8: =J6+J7 -> 262035.73 | ... L8: =L6+L7 -> 291281.25
B9: Gross Margin (%) | C9: =C8/C6 -> 0.56 | D9: =D8/D6 -> 0.565 | E9: =E8/E6 -> 0.57 | F9: =F8/F6 -> 0.575 | G9: =G8/G6 -> 0.58 | H9: =H8/H6 -> 0.583 | I9: =I8/I6 -> 0.586 | J9: =J8/J6 -> 0.589 | ... L9: =L8/L6 -> 0.593
B11: Selling, General & Administrative | C11: =-C6*Assumptions!C26 -> -91562.014 | D11: =-D6*Assumptions!D26 -> -97020.965 | E11: =-E6*Assumptions!E26 -> -104923.64 | F11: =-F6*Assumptions!F26 -> -111931.98 | G11: =-G6*Assumptions!G26 -> -119964.54 | H11: =-H6*Assumptions!H26 -> -126203.18 | I11: =-I6*Assumptions!I26 -> -132355.31 | J11: =-J6*Assumptions!J26 -> -138358.42 | ... L11: =-L6*Assumptions!L26 -> -150798.22
B12: EBITDA | C12: =C8+C11 -> 59246.009 | D12: =D8+D11 -> 66611.409 | E12: =E8+E11 -> 76308.098 | F12: =F8+F11 -> 86101.525 | G12: =G8+G11 -> 97471.192 | H12: =H8+H11 -> 105899.2 | I12: =I8+I11 -> 114651.74 | J12: =J8+J11 -> 123677.3 | ... L12: =L8+L11 -> 140483.03
B13: EBITDA Margin (%) | C13: =C12/C6 -> 0.22 | D13: =D12/D6 -> 0.23 | E13: =E12/E6 -> 0.24 | F13: =F12/F6 -> 0.25 | G13: =G12/G6 -> 0.26 | H13: =H12/H6 -> 0.266 | I13: =I12/I6 -> 0.272 | J13: =J12/J6 -> 0.278 | ... L13: =L12/L6 -> 0.286
B15: Depreciation & Amortization | C15: =-C6*Assumptions!C27 -> -10772.002 | D15: =-D6*Assumptions!D27 -> -11294.978 | E15: =-E6*Assumptions!E27 -> -12082.116 | F15: =-F6*Assumptions!F27 -> -12743.026 | G15: =-G6*Assumptions!G27 -> -13496.011 | H15: =-H6*Assumptions!H27 -> -14332.223 | I15: =-I6*Assumptions!I27 -> -14752.981 | J15: =-J6*Assumptions!J27 -> -15570.884 | ... L15: =-L6*Assumptions!L27 -> -16700.78
B16: EBIT | C16: =C12+C15 -> 48474.007 | D16: =D12+D15 -> 55316.431 | E16: =E12+E15 -> 64225.983 | F16: =F12+F15 -> 73358.499 | G16: =G12+G15 -> 83975.181 | H16: =H12+H15 -> 91566.979 | I16: =I12+I15 -> 99898.756 | J16: =J12+J15 -> 108106.42 | ... L16: =L12+L15 -> 123782.25
B17: EBIT Margin (%) | C17: =C16/C6 -> 0.18 | D17: =D16/D6 -> 0.191 | E17: =E16/E6 -> 0.202 | F17: =F16/F6 -> 0.213 | G17: =G16/G6 -> 0.224 | H17: =H16/H6 -> 0.23 | I17: =I16/I6 -> 0.237 | J17: =J16/J6 -> 0.243 | ... L17: =L16/L6 -> 0.252
B19: Interest Expense, Net | C19: ='Debt Schedule'!C15 -> -3162.5 | D19: ='Debt Schedule'!D15 -> -3300 | E19: ='Debt Schedule'!E15 -> -3300 | F19: ='Debt Schedule'!F15 -> -3300 | G19: ='Debt Schedule'!G15 -> -3300 | H19: ='Debt Schedule'!H15 -> -3300 | I19: ='Debt Schedule'!I15 -> -3162.5 | J19: ='Debt Schedule'!J15 -> -2887.5 | ... L19: ='Debt Schedule'!L15 -> -2337.5
B20: Pre-Tax Income (EBT) | C20: =C16+C19 -> 45311.507 | D20: =D16+D19 -> 52016.431 | E20: =E16+E19 -> 60925.983 | F20: =F16+F19 -> 70058.499 | G20: =G16+G19 -> 80675.181 | H20: =H16+H19 -> 88266.979 | I20: =I16+I19 -> 96736.256 | J20: =J16+J19 -> 105218.92 | ... L20: =L16+L19 -> 121444.75
B21: Income Tax Expense | C21: =-C20*Assumptions!C28 -> -11780.992 | D21: =-D20*Assumptions!D28 -> -13264.19 | E21: =-E20*Assumptions!E28 -> -15536.126 | F21: =-F20*Assumptions!F28 -> -17514.625 | G21: =-G20*Assumptions!G28 -> -20168.795 | H21: =-H20*Assumptions!H28 -> -21625.41 | I21: =-I20*Assumptions!I28 -> -23700.383 | J21: =-J20*Assumptions!J28 -> -25252.541 | ... L21: =-L20*Assumptions!L28 -> -29146.74
B22: Net Income | C22: =C20+C21 -> 33530.515 | D22: =D20+D21 -> 38752.241 | E22: =E20+E21 -> 45389.857 | F22: =F20+F21 -> 52543.874 | G22: =G20+G21 -> 60506.386 | H22: =H20+H21 -> 66641.569 | I22: =I20+I21 -> 73035.873 | J22: =J20+J21 -> 79966.38 | ... L22: =L20+L21 -> 92298.011
B23: Net Margin (%) | C23: =C22/C6 -> 0.12450988 | D23: =D22/D6 -> 0.13380614 | E23: =E22/E6 -> 0.14275766 | F23: =F22/F6 -> 0.15256372 | G23: =G22/G6 -> 0.16139805 | H23: =H22/H6 -> 0.16739179 | I23: =I22/I6 -> 0.17327045 | J23: =J22/J6 -> 0.17974724 | ... L23: =L22/L6 -> 0.18790334
B25: Diluted Shares Outstanding (mm) | C25: =Assumptions!$C$42 -> 48.5 | D25: =Assumptions!$C$42 -> 48.5 | E25: =Assumptions!$C$42 -> 48.5 | F25: =Assumptions!$C$42 -> 48.5 | G25: =Assumptions!$C$42 -> 48.5 | H25: =Assumptions!$C$42 -> 48.5 | I25: =Assumptions!$C$42 -> 48.5 | J25: =Assumptions!$C$42 -> 48.5 | ... L25: =Assumptions!$C$42 -> 48.5
B26: Diluted EPS ($) | C26: =C22/(C25*1000) -> 0.69135083 | D26: =D22/(D25*1000) -> 0.79901527 | E26: =E22/(E25*1000) -> 0.93587334 | F26: =F22/(F25*1000) -> 1.0833789 | G26: =G22/(G25*1000) -> 1.2475543 | H26: =H22/(H25*1000) -> 1.374053 | I26: =I22/(I25*1000) -> 1.5058943 | J26: =J22/(J25*1000) -> 1.6487913 | ... L26: =L22/(L25*1000) -> 1.9030518

Sheet Working Capital
B1: WORKING CAPITAL SCHEDULE
C3: ACTUAL | H3: PROJECTED
B4: ($ in 000s, unless noted) | C4: 2021 | D4: 2022 | E4: 2023 | F4: 2024 | G4: 2025 | H4: 2026 | I4: 2027 | J4: 2028 | K4: 2029 | L4: 2030
B5: ■ Blue = Input ■ Black = Formula ■ Green = Link to Another Sheet
B6: Days-Based Drivers
B7: Days Sales Outstanding (DSO) | C7: 36.5 | D7: =$C$7 -> 36.5 | E7: =$C$7 -> 36.5 | F7: =$C$7 -> 36.5 | G7: =$C$7 -> 36.5 | H7: =$C$7 -> 36.5 | I7: =$C$7 -> 36.5 | J7: =$C$7 -> 36.5 | K7: =$C$7 -> 36.5 | L7: =$C$7 -> 36.5
B8: Days Inventory Outstanding (DIO) | C8: 54.75 | D8: =$C$8 -> 54.75 | E8: =$C$8 -> 54.75 | F8: =$C$8 -> 54.75 | G8: =$C$8 -> 54.75 | H8: =$C$8 -> 54.75 | I8: =$C$8 -> 54.75 | J8: =$C$8 -> 54.75 | K8: =$C$8 -> 54.75 | L8: =$C$8 -> 54.75
B9: Days Payable Outstanding (DPO) | C9: 43.8 | D9: =$C$9 -> 43.8 | E9: =$C$9 -> 43.8 | F9: =$C$9 -> 43.8 | G9: =$C$9 -> 43.8 | H9: =$C$9 -> 43.8 | I9: =$C$9 -> 43.8 | J9: =$C$9 -> 43.8 | K9: =$C$9 -> 43.8 | L9: =$C$9 -> 43.8
B11: Working Capital Build
B12: Accounts Receivable (= Revenue ÷ 365 × DSO) | C12: ='Income Statement'!C6/365*C7 -> 26930.004 | D12: ='Income Statement'!D6/365*D7 -> 28961.482 | E12: ='Income Statement'!E6/365*E7 -> 31795.041 | F12: ='Income Statement'!F6/365*F7 -> 34440.61 | G12: ='Income Statement'!G6/365*G7 -> 37488.92 | H12: ='Income Statement'!H6/365*H7 -> 39811.73 | I12: ='Income Statement'!I6/365*I7 -> 42151.374 | J12: ='Income Statement'!J6/365*J7 -> 44488.239 | ... L12: ='Income Statement'!L6/365*L7 -> 49119.941
B13: Inventory (= COGS ÷ 365 × DIO) | C13: =-'Income Statement'!C7/365*C8 -> 17773.803 | D13: =-'Income Statement'!D7/365*D8 -> 18897.367 | E13: =-'Income Statement'!E7/365*E8 -> 20507.801 | F13: =-'Income Statement'!F7/365*F8 -> 21955.889 | G13: =-'Income Statement'!G7/365*G8 -> 23618.02 | H13: =-'Income Statement'!H7/365*H8 -> 24902.237 | I13: =-'Income Statement'!I7/365*I8 -> 26176.003 | J13: =-'Income Statement'!J7/365*J8 -> 27426.999 | ... L13: =-'Income Statement'!L7/365*L8 -> 29987.724
B14: Accounts Payable (= COGS ÷ 365 × DPO) | C14: =-'Income Statement'!C7/365*C9 -> 14219.042 | D14: =-'Income Statement'!D7/365*D9 -> 15117.894 | E14: =-'Income Statement'!E7/365*E9 -> 16406.241 | F14: =-'Income Statement'!F7/365*F9 -> 17564.711 | G14: =-'Income Statement'!G7/365*G9 -> 18894.416 | H14: =-'Income Statement'!H7/365*H9 -> 19921.79 | I14: =-'Income Statement'!I7/365*I9 -> 20940.803 | J14: =-'Income Statement'!J7/365*J9 -> 21941.599 | ... L14: =-'Income Statement'!L7/365*L9 -> 23990.179
B16: Net Working Capital
B17: Net Working Capital (AR + Inventory − AP) | C17: =C12+C13-C14 -> 30484.765 | D17: =D12+D13-D14 -> 32740.955 | E17: =E12+E13-E14 -> 35896.601 | F17: =F12+F13-F14 -> 38831.788 | G17: =G12+G13-G14 -> 42212.524 | H17: =H12+H13-H14 -> 44792.178 | I17: =I12+I13-I14 -> 47386.575 | J17: =J12+J13-J14 -> 49973.639 | ... L17: =L12+L13-L14 -> 55117.486
B18: (Increase) / Decrease in NWC | D18: =-(D17-C17) -> -2256.1909 | E18: =-(E17-D17) -> -3155.6459 | F18: =-(F17-E17) -> -2935.1865 | G18: =-(G17-F17) -> -3380.7361 | H18: =-(H17-G17) -> -2579.6536 | I18: =-(I17-H17) -> -2594.397 | J18: =-(J17-I17) -> -2587.0642 | K18: =-(K17-J17) -> -2589.1979 | L18: =-(L17-K17) -> -2554.6491

Sheet Debt Schedule
B1: DEBT SCHEDULE
C3: ACTUAL | H3: PROJECTED
B4: ($ in 000s, unless noted) | C4: 2021 | D4: 2022 | E4: 2023 | F4: 2024 | G4: 2025 | H4: 2026 | I4: 2027 | J4: 2028 | K4: 2029 | L4: 2030
B5: ■ Blue = Input ■ Black = Formula ■ Green = Link to Another Sheet
B6: Long-Term Debt Roll-Forward
B7: Opening Debt Balance | C7: =Assumptions!$C$43 -> 55000 | D7: =C10 -> 60000 | E7: =D10 -> 60000 | F7: =E10 -> 60000 | G7: =F10 -> 60000 | H7: =G10 -> 60000 | I7: =H10 -> 60000 | J7: =I10 -> 55000 | K7: =J10 -> 50000 | L7: =K10 -> 45000
B8: (+) New Borrowings | C8: 5000 | D8: 0 | E8: 0 | F8: 0 | G8: 0 | H8: 0 | I8: 0 | J8: 0 | K8: 0 | L8: 0
B9: (−) Scheduled Repayments | C9: 0 | D9: 0 | E9: 0 | F9: 0 | G9: 0 | H9: 0 | I9: -5000 | J9: -5000 | K9: -5000 | L9: -5000
B10: Ending Debt Balance | C10: =C7+C8+C9 -> 60000 | D10: =D7+D8+D9 -> 60000 | E10: =E7+E8+E9 -> 60000 | F10: =F7+F8+F9 -> 60000 | G10: =G7+G8+G9 -> 60000 | H10: =H7+H8+H9 -> 60000 | I10: =I7+I8+I9 -> 55000 | J10: =J7+J8+J9 -> 50000 | ... L10: =L7+L8+L9 -> 40000
B12: Interest Calculation
B13: Interest Rate (Pre-Tax Cost of Debt) | C13: =Assumptions!$C$37 -> 0.055 | D13: =Assumptions!$C$37 -> 0.055 | E13: =Assumptions!$C$37 -> 0.055 | F13: =Assumptions!$C$37 -> 0.055 | G13: =Assumptions!$C$37 -> 0.055 | H13: =Assumptions!$C$37 -> 0.055 | I13: =Assumptions!$C$37 -> 0.055 | J13: =Assumptions!$C$37 -> 0.055 | ... L13: =Assumptions!$C$37 -> 0.055
B14: Average Debt Balance | C14: =AVERAGE(C7,C10) -> 57500 | D14: =AVERAGE(D7,D10) -> 60000 | E14: =AVERAGE(E7,E10) -> 60000 | F14: =AVERAGE(F7,F10) -> 60000 | G14: =AVERAGE(G7,G10) -> 60000 | H14: =AVERAGE(H7,H10) -> 60000 | I14: =AVERAGE(I7,I10) -> 57500 | J14: =AVERAGE(J7,J10) -> 52500 | ... L14: =AVERAGE(L7,L10) -> 42500
B15: Interest Expense | C15: =-C14*C13 -> -3162.5 | D15: =-D14*D13 -> -3300 | E15: =-E14*E13 -> -3300 | F15: =-F14*F13 -> -3300 | G15: =-G14*G13 -> -3300 | H15: =-H14*H13 -> -3300 | I15: =-I14*I13 -> -3162.5 | J15: =-J14*J13 -> -2887.5 | ... L15: =-L14*L13 -> -2337.5

Sheet Balance Sheet
B1: BALANCE SHEET
C3: ACTUAL | H3: PROJECTED
B4: ($ in 000s, unless noted) | C4: 2021 | D4: 2022 | E4: 2023 | F4: 2024 | G4: 2025 | H4: 2026 | I4: 2027 | J4: 2028 | K4: 2029 | L4: 2030
B5: ■ Blue = Input ■ Black = Formula ■ Green = Link to Another Sheet
B6: Assets
B7: Cash & Cash Equivalents | C7: 42300 | D7: ='Cash Flow'!D25 -> 78506.435 | E7: ='Cash Flow'!E25 -> 120422.7 | F7: ='Cash Flow'!F25 -> 170031.38 | G7: ='Cash Flow'!G25 -> 227157.03 | H7: ='Cash Flow'!H25 -> 291218.95 | I7: ='Cash Flow'!I25 -> 356660.43 | J7: ='Cash Flow'!J25 -> 429039.74 | K7: ='Cash Flow'!K25 -> 507708.06 | L7: ='Cash Flow'!L25 -> 592451.42
B8: Accounts Receivable | C8: ='Working Capital'!C12 -> 26930.004 | D8: ='Working Capital'!D12 -> 28961.482 | E8: ='Working Capital'!E12 -> 31795.041 | F8: ='Working Capital'!F12 -> 34440.61 | G8: ='Working Capital'!G12 -> 37488.92 | H8: ='Working Capital'!H12 -> 39811.73 | I8: ='Working Capital'!I12 -> 42151.374 | J8: ='Working Capital'!J12 -> 44488.239 | ... L8: ='Working Capital'!L12 -> 49119.941
B9: Inventory | C9: ='Working Capital'!C13 -> 17773.803 | D9: ='Working Capital'!D13 -> 18897.367 | E9: ='Working Capital'!E13 -> 20507.801 | F9: ='Working Capital'!F13 -> 21955.889 | G9: ='Working Capital'!G13 -> 23618.02 | H9: ='Working Capital'!H13 -> 24902.237 | I9: ='Working Capital'!I13 -> 26176.003 | J9: ='Working Capital'!J13 -> 27426.999 | ... L9: ='Working Capital'!L13 -> 29987.724
B10: Total Current Assets | C10: =SUM(C7:C9) -> 87003.807 | D10: =SUM(D7:D9) -> 126365.28 | E10: =SUM(E7:E9) -> 172725.54 | F10: =SUM(F7:F9) -> 226427.88 | G10: =SUM(G7:G9) -> 288263.97 | H10: =SUM(H7:H9) -> 355932.92 | I10: =SUM(I7:I9) -> 424987.8 | J10: =SUM(J7:J9) -> 500954.98 | ... L10: =SUM(L7:L9) -> 671559.09
B11: Property, Plant & Equipment, net | C11: 180000 | D11: =C11+'Income Statement'!D6*Assumptions!D29+'Income Statement'!D15 -> 180289.61 | E11: =D11+'Income Statement'!E6*Assumptions!E29+'Income Statement'!E15 -> 180607.57 | F11: =E11+'Income Statement'!F6*Assumptions!F29+'Income Statement'!F15 -> 180607.57 | G11: =F11+'Income Statement'!G6*Assumptions!G29+'Income Statement'!G15 -> 180607.57 | H11: =G11+'Income Statement'!H6*Assumptions!H29+'Income Statement'!H15 -> 180607.57 | I11: =H11+'Income Statement'!I6*Assumptions!I29+'Income Statement'!I15 -> 180607.57 | J11: =I11+'Income Statement'!J6*Assumptions!J29+'Income Statement'!J15 -> 180607.57 | K11: =J11+'Income Statement'!K6*Assumptions!K29+'Income Statement'!K15 -> 180607.57 | L11: =K11+'Income Statement'!L6*Assumptions!L29+'Income Statement'!L15 -> 180607.57
B12: Total Assets | C12: =C10+C11 -> 267003.81 | D12: =D10+D11 -> 306654.9 | E12: =E10+E11 -> 353333.1 | F12: =F10+F11 -> 407035.45 | G12: =G10+G11 -> 468871.54 | H12: =H10+H11 -> 536540.48 | I12: =I10+I11 -> 605595.37 | J12: =J10+J11 -> 681562.54 | ... L12: =L10+L11 -> 852166.65
B14: Liabilities & Shareholders' Equity
B15: Accounts Payable | C15: ='Working Capital'!C14 -> 14219.042 | D15: ='Working Capital'!D14 -> 15117.894 | E15: ='Working Capital'!E14 -> 16406.241 | F15: ='Working Capital'!F14 -> 17564.711 | G15: ='Working Capital'!G14 -> 18894.416 | H15: ='Working Capital'!H14 -> 19921.79 | I15: ='Working Capital'!I14 -> 20940.803 | J15: ='Working Capital'!J14 -> 21941.599 | ... L15: ='Working Capital'!L14 -> 23990.179
B16: Long-Term Debt | C16: ='Debt Schedule'!C10 -> 60000 | D16: ='Debt Schedule'!D10 -> 60000 | E16: ='Debt Schedule'!E10 -> 60000 | F16: ='Debt Schedule'!F10 -> 60000 | G16: ='Debt Schedule'!G10 -> 60000 | H16: ='Debt Schedule'!H10 -> 60000 | I16: ='Debt Schedule'!I10 -> 55000 | J16: ='Debt Schedule'!J10 -> 50000 | ... L16: ='Debt Schedule'!L10 -> 40000
B17: Total Liabilities | C17: =C15+C16 -> 74219.042 | D17: =D15+D16 -> 75117.894 | E17: =E15+E16 -> 76406.241 | F17: =F15+F16 -> 77564.711 | G17: =G15+G16 -> 78894.416 | H17: =H15+H16 -> 79921.79 | I17: =I15+I16 -> 75940.803 | J17: =J15+J16 -> 71941.599 | ... L17: =L15+L16 -> 63990.179
B18: Common Stock & APIC | C18: =Assumptions!$C$44 -> 50000 | D18: =Assumptions!$C$44 -> 50000 | E18: =Assumptions!$C$44 -> 50000 | F18: =Assumptions!$C$44 -> 50000 | G18: =Assumptions!$C$44 -> 50000 | H18: =Assumptions!$C$44 -> 50000 | I18: =Assumptions!$C$44 -> 50000 | J18: =Assumptions!$C$44 -> 50000 | ... L18: =Assumptions!$C$44 -> 50000
B19: Retained Earnings | C19: 142784.76 | D19: =C19+'Income Statement'!D22 -> 181537.01 | E19: =D19+'Income Statement'!E22 -> 226926.86 | F19: =E19+'Income Statement'!F22 -> 279470.74 | G19: =F19+'Income Statement'!G22 -> 339977.12 | H19: =G19+'Income Statement'!H22 -> 406618.69 | I19: =H19+'Income Statement'!I22 -> 479654.57 | J19: =I19+'Income Statement'!J22 -> 559620.94 | K19: =J19+'Income Statement'!K22 -> 645878.46 | L19: =K19+'Income Statement'!L22 -> 738176.47
B20: Total Shareholders' Equity | C20: =C18+C19 -> 192784.76 | D20: =D18+D19 -> 231537.01 | E20: =E18+E19 -> 276926.86 | F20: =F18+F19 -> 329470.74 | G20: =G18+G19 -> 389977.12 | H20: =H18+H19 -> 456618.69 | I20: =I18+I19 -> 529654.57 | J20: =J18+J19 -> 609620.94 | ... L20: =L18+L19 -> 788176.47
B21: Total Liabilities & Equity | C21: =C17+C20 -> 267003.81 | D21: =D17+D20 -> 306654.9 | E21: =E17+E20 -> 353333.1 | F21: =F17+F20 -> 407035.45 | G21: =G17+G20 -> 468871.54 | H21: =H17+H20 -> 536540.48 | I21: =I17+I20 -> 605595.37 | J21: =J17+J20 -> 681562.54 | ... L21: =L17+L20 -> 852166.65
B22: Balance Check | C22: =C12-C21 -> 2.799998e-05 | D22: =D12-D21 -> 2.8000039e-05 | E22: =E12-E21 -> 2.8000039e-05 | F22: =F12-F21 -> 2.799998e-05 | G22: =G12-G21 -> 2.799998e-05 | H22: =H12-H21 -> 2.799998e-05 | I22: =I12-I21 -> 2.799998e-05 | J22: =J12-J21 -> 2.8000097e-05 | ... L22: =L12-L21 -> 2.8000097e-05

Sheet Cash Flow
B1: CASH FLOW STATEMENT
C3: ACTUAL | H3: PROJECTED
B4: ($ in 000s, unless noted) | C4: 2021 | D4: 2022 | E4: 2023 | F4: 2024 | G4: 2025 | H4: 2026 | I4: 2027 | J4: 2028 | K4: 2029 | L4: 2030
B5: ■ Blue = Input ■ Black = Formula ■ Green = Link to Another Sheet
B6: Cash Flow from Operating Activities
B7: Net Income | C7: n.a. | D7: ='Income Statement'!D22 -> 38752.241 | E7: ='Income Statement'!E22 -> 45389.857 | F7: ='Income Statement'!F22 -> 52543.874 | G7: ='Income Statement'!G22 -> 60506.386 | H7: ='Income Statement'!H22 -> 66641.569 | I7: ='Income Statement'!I22 -> 73035.873 | J7: ='Income Statement'!J22 -> 79966.38 | K7: ='Income Statement'!K22 -> 86257.516 | L7: ='Income Statement'!L22 -> 92298.011
B8: Plus: Depreciation & Amortization | C8: n.a. | D8: =-'Income Statement'!D15 -> 11294.978 | E8: =-'Income Statement'!E15 -> 12082.116 | F8: =-'Income Statement'!F15 -> 12743.026 | G8: =-'Income Statement'!G15 -> 13496.011 | H8: =-'Income Statement'!H15 -> 14332.223 | I8: =-'Income Statement'!I15 -> 14752.981 | J8: =-'Income Statement'!J15 -> 15570.884 | K8: =-'Income Statement'!K15 -> 15918.201 | L8: =-'Income Statement'!L15 -> 16700.78
B9: (Increase) / Decrease in Accounts Receivable | C9: n.a. | D9: =-('Balance Sheet'!D8-'Balance Sheet'!C8) -> -2031.478 | E9: =-('Balance Sheet'!E8-'Balance Sheet'!D8) -> -2833.559 | F9: =-('Balance Sheet'!F8-'Balance Sheet'!E8) -> -2645.569 | G9: =-('Balance Sheet'!G8-'Balance Sheet'!F8) -> -3048.31 | H9: =-('Balance Sheet'!H8-'Balance Sheet'!G8) -> -2322.8101 | I9: =-('Balance Sheet'!I8-'Balance Sheet'!H8) -> -2339.6438 | J9: =-('Balance Sheet'!J8-'Balance Sheet'!I8) -> -2336.865 | K9: =-('Balance Sheet'!K8-'Balance Sheet'!J8) -> -2329.9999 | L9: =-('Balance Sheet'!L8-'Balance Sheet'!K8) -> -2301.7022
B10: (Increase) / Decrease in Inventory | C10: n.a. | D10: =-('Balance Sheet'!D9-'Balance Sheet'!C9) -> -1123.5644 | E10: =-('Balance Sheet'!E9-'Balance Sheet'!D9) -> -1610.4344 | F10: =-('Balance Sheet'!F9-'Balance Sheet'!E9) -> -1448.0874 | G10: =-('Balance Sheet'!G9-'Balance Sheet'!F9) -> -1662.1307 | H10: =-('Balance Sheet'!H9-'Balance Sheet'!G9) -> -1284.2176 | I10: =-('Balance Sheet'!I9-'Balance Sheet'!H9) -> -1273.766 | J10: =-('Balance Sheet'!J9-'Balance Sheet'!I9) -> -1250.9961 | K10: =-('Balance Sheet'!K9-'Balance Sheet'!J9) -> -1295.9902 | L10: =-('Balance Sheet'!L9-'Balance Sheet'!K9) -> -1264.7345
B11: Increase / (Decrease) in Accounts Payable | C11: n.a. | D11: ='Balance Sheet'!D15-'Balance Sheet'!C15 -> 898.85149 | E11: ='Balance Sheet'!E15-'Balance Sheet'!D15 -> 1288.3476 | F11: ='Balance Sheet'!F15-'Balance Sheet'!E15 -> 1158.4699 | G11: ='Balance Sheet'!G15-'Balance Sheet'!F15 -> 1329.7046 | H11: ='Balance Sheet'!H15-'Balance Sheet'!G15 -> 1027.3741 | I11: ='Balance Sheet'!I15-'Balance Sheet'!H15 -> 1019.0128 | J11: ='Balance Sheet'!J15-'Balance Sheet'!I15 -> 1000.7969 | K11: ='Balance Sheet'!K15-'Balance Sheet'!J15 -> 1036.7922 | L11: ='Balance Sheet'!L15-'Balance Sheet'!K15 -> 1011.7876
B12: Cash Flow from Operations | C12: n.a. | D12: =SUM(D7:D11) -> 47791.028 | E12: =SUM(E7:E11) -> 54316.327 | F12: =SUM(F7:F11) -> 62351.714 | G12: =SUM(G7:G11) -> 70621.661 | H12: =SUM(H7:H11) -> 78394.139 | I12: =SUM(I7:I11) -> 85194.457 | J12: =SUM(J7:J11) -> 92950.199 | K12: =SUM(K7:K11) -> 99586.52 | L12: =SUM(L7:L11) -> 106444.14
B14: Cash Flow from Investing Activities
B15: Capital Expenditures | C15: n.a. | D15: =-'Income Statement'!D6*Assumptions!D29 -> -11584.593 | E15: =-'Income Statement'!E6*Assumptions!E29 -> -12400.066 | F15: =-'Income Statement'!F6*Assumptions!F29 -> -12743.026 | G15: =-'Income Statement'!G6*Assumptions!G29 -> -13496.011 | H15: =-'Income Statement'!H6*Assumptions!H29 -> -14332.223 | I15: =-'Income Statement'!I6*Assumptions!I29 -> -14752.981 | J15: =-'Income Statement'!J6*Assumptions!J29 -> -15570.884 | K15: =-'Income Statement'!K6*Assumptions!K29 -> -15918.201 | L15: =-'Income Statement'!L6*Assumptions!L29 -> -16700.78
B16: Cash Flow from Investing | C16: n.a. | D16: =D15 -> -11584.593 | E16: =E15 -> -12400.066 | F16: =F15 -> -12743.026 | G16: =G15 -> -13496.011 | H16: =H15 -> -14332.223 | I16: =I15 -> -14752.981 | J16: =J15 -> -15570.884 | K16: =K15 -> -15918.201 | L16: =L15 -> -16700.78
B18: Cash Flow from Financing Activities
B19: Debt Issuance / (Repayment) | C19: n.a. | D19: ='Debt Schedule'!D8+'Debt Schedule'!D9 -> 0 | E19: ='Debt Schedule'!E8+'Debt Schedule'!E9 -> 0 | F19: ='Debt Schedule'!F8+'Debt Schedule'!F9 -> 0 | G19: ='Debt Schedule'!G8+'Debt Schedule'!G9 -> 0 | H19: ='Debt Schedule'!H8+'Debt Schedule'!H9 -> 0 | I19: ='Debt Schedule'!I8+'Debt Schedule'!I9 -> -5000 | J19: ='Debt Schedule'!J8+'Debt Schedule'!J9 -> -5000 | K19: ='Debt Schedule'!K8+'Debt Schedule'!K9 -> -5000 | L19: ='Debt Schedule'!L8+'Debt Schedule'!L9 -> -5000
B20: Cash Flow from Financing | C20: n.a. | D20: =D19 -> 0 | E20: =E19 -> 0 | F20: =F19 -> 0 | G20: =G19 -> 0 | H20: =H19 -> 0 | I20: =I19 -> -5000 | J20: =J19 -> -5000 | K20: =K19 -> -5000 | L20: =L19 -> -5000
B22: Net Change in Cash
B23: Net Increase / (Decrease) in Cash | C23: n.a. | D23: =D12+D16+D20 -> 36206.435 | E23: =E12+E16+E20 -> 41916.261 | F23: =F12+F16+F20 -> 49608.688 | G23: =G12+G16+G20 -> 57125.649 | H23: =H12+H16+H20 -> 64061.916 | I23: =I12+I16+I20 -> 65441.476 | J23: =J12+J16+J20 -> 72379.315 | K23: =K12+K16+K20 -> 78668.319 | L23: =L12+L16+L20 -> 84743.362
B24: Beginning Cash Balance | C24: n.a. | D24: ='Balance Sheet'!C7 -> 42300 | E24: ='Balance Sheet'!D7 -> 78506.435 | F24: ='Balance Sheet'!E7 -> 120422.7 | G24: ='Balance Sheet'!F7 -> 170031.38 | H24: ='Balance Sheet'!G7 -> 227157.03 | I24: ='Balance Sheet'!H7 -> 291218.95 | J24: ='Balance Sheet'!I7 -> 356660.43 | K24: ='Balance Sheet'!J7 -> 429039.74 | L24: ='Balance Sheet'!K7 -> 507708.06
B25: Ending Cash Balance | C25: n.a. | D25: =D23+D24 -> 78506.435 | E25: =E23+E24 -> 120422.7 | F25: =F23+F24 -> 170031.38 | G25: =G23+G24 -> 227157.03 | H25: =H23+H24 -> 291218.95 | I25: =I23+I24 -> 356660.43 | J25: =J23+J24 -> 429039.74 | K25: =K23+K24 -> 507708.06 | L25: =L23+L24 -> 592451.42

Sheet DCF Valuation
B1: DISCOUNTED CASH FLOW VALUATION
C3: ACTUAL | H3: PROJECTED
B4: ($ in 000s, unless noted) | C4: 2021 | D4: 2022 | E4: 2023 | F4: 2024 | G4: 2025 | H4: 2026 | I4: 2027 | J4: 2028 | K4: 2029 | L4: 2030
B5: ■ Blue = Input ■ Black = Formula ■ Green = Link to Another Sheet
B6: Unlevered Free Cash Flow (Projection Period)
B7: EBIT | H7: ='Income Statement'!H16 -> 91566.979 | I7: ='Income Statement'!I16 -> 99898.756 | J7: ='Income Statement'!J16 -> 108106.42 | K7: ='Income Statement'!K16 -> 116109.23 | L7: ='Income Statement'!L16 -> 123782.25
B8: Less: Unlevered Taxes | H8: =-H7*Assumptions!H28 -> -22433.91 | I8: =-I7*Assumptions!I28 -> -24475.195 | J8: =-J7*Assumptions!J28 -> -25945.541 | K8: =-K7*Assumptions!K28 -> -27866.216 | L8: =-L7*Assumptions!L28 -> -29707.74
B9: NOPAT | H9: =H7+H8 -> 69133.069 | I9: =I7+I8 -> 75423.561 | J9: =J7+J8 -> 82160.88 | K9: =K7+K8 -> 88243.016 | L9: =L7+L8 -> 94074.511
B10: Plus: D&A | H10: =-'Income Statement'!H15 -> 14332.223 | I10: =-'Income Statement'!I15 -> 14752.981 | J10: =-'Income Statement'!J15 -> 15570.884 | K10: =-'Income Statement'!K15 -> 15918.201 | L10: =-'Income Statement'!L15 -> 16700.78
B11: Less: Capital Expenditures | H11: =-'Income Statement'!H6*Assumptions!H29 -> -14332.223 | I11: =-'Income Statement'!I6*Assumptions!I29 -> -14752.981 | J11: =-'Income Statement'!J6*Assumptions!J29 -> -15570.884 | K11: =-'Income Statement'!K6*Assumptions!K29 -> -15918.201 | L11: =-'Income Statement'!L6*Assumptions!L29 -> -16700.78
B12: Less: Increase in Net Working Capital | H12: ='Cash Flow'!H9+'Cash Flow'!H10+'Cash Flow'!H11 -> -2579.6536 | I12: ='Cash Flow'!I9+'Cash Flow'!I10+'Cash Flow'!I11 -> -2594.397 | J12: ='Cash Flow'!J9+'Cash Flow'!J10+'Cash Flow'!J11 -> -2587.0642 | K12: ='Cash Flow'!K9+'Cash Flow'!K10+'Cash Flow'!K11 -> -2589.1979 | L12: ='Cash Flow'!L9+'Cash Flow'!L10+'Cash Flow'!L11 -> -2554.6491
B13: Unlevered Free Cash Flow | H13: =H9+H10+H11+H12 -> 66553.416 | I13: =I9+I10+I11+I12 -> 72829.164 | J13: =J9+J10+J11+J12 -> 79573.815 | K13: =K9+K10+K11+K12 -> 85653.819 | L13: =L9+L10+L11+L12 -> 91519.862
B14: Discount Period | H14: 1 | I14: 2 | J14: 3 | K14: 4 | L14: 5
B15: Discount Factor | H15: =1/(1+Assumptions!$C$40)^H14 -> 0.90947522 | I15: =1/(1+Assumptions!$C$40)^I14 -> 0.82714517 | J15: =1/(1+Assumptions!$C$40)^J14 -> 0.75226804 | K15: =1/(1+Assumptions!$C$40)^K14 -> 0.68416914 | L15: =1/(1+Assumptions!$C$40)^L14 -> 0.62223488
B16: PV of Free Cash Flow | H16: =H13*H15 -> 60528.682 | I16: =I13*I15 -> 60240.291 | J16: =J13*J15 -> 59860.838 | K16: =K13*K15 -> 58601.699 | L16: =L13*L15 -> 56946.85
B18: Valuation Summary
B19: Sum of PV of FCF (2026–2030) | C19: =SUM(H16:L16) -> 296178.36
B20: Terminal Value (Gordon Growth) | C20: =L13*(1+Assumptions!$C$41)/(Assumptions!$C$40-Assumptions!$C$41) -> 1223291.3
B21: PV of Terminal Value | C21: =C20*L15 -> 761174.49
B22: Enterprise Value | C22: =C19+C21 -> 1057352.8
B23: % of EV from Terminal Value | C23: =C21/C22 -> 0.71988692
B25: Less: Net Debt / (Net Cash) | C25: ='Debt Schedule'!G10-'Balance Sheet'!G7 -> -167157.03
B26: Implied Equity Value | C26: =C22-C25 -> 1224509.9
B27: Diluted Shares Outstanding (mm) | C27: =Assumptions!$C$42 -> 48.5
B28: Implied Share Price ($) | C28: =C26/(C27*1000) -> 25.247626

Sheet Comparables
B1: COMPARABLE COMPANY VALUATION
B3: ■ Blue = Input ■ Black = Formula ■ Green = Link to Another Sheet
B6: Selected Public Comparables
B7: Company | C7: EV / EBITDA | D7: EV / Revenue | E7: P / E
B8: Sterling & Vane Group | C8: 11.5 | D8: 3.2 | E8: 18.5
B9: Whitmore Capital Partners | C9: 10.8 | D9: 2.9 | E9: 17.2
B10: Blackwood Estates plc | C10: 12.2 | D10: 3.5 | E10: 19.8
B11: Ainsley Textile Holdings | C11: 9.5 | D11: 2.4 | E11: 15.6
B12: Crown & Thistle Wealth | C12: 13 | D12: 3.8 | E12: 20.5
B13: Mean | C13: =AVERAGE(C8:C12) -> 11.4 | D13: =AVERAGE(D8:D12) -> 3.16 | E13: =AVERAGE(E8:E12) -> 18.32
B14: Median | C14: =MEDIAN(C8:C12) -> 11.5 | D14: =MEDIAN(D8:D12) -> 3.2 | E14: =MEDIAN(E8:E12) -> 18.5
B16: Implied Valuation — Trading Comparables (Applied to FY2026E)
B17: FY2026E EBITDA ($000s) | C17: ='Income Statement'!H12 -> 105899.2
B18: FY2026E Revenue ($000s) | C18: ='Income Statement'!H6 -> 398117.3
B19: FY2026E Diluted EPS ($) | C19: ='Income Statement'!H26 -> 1.374053
B20: Net Debt / (Net Cash), Current ($000s) | C20: ='Debt Schedule'!G10-'Balance Sheet'!G7 -> -167157.03
B22: Method | C22: Implied EV | D22: Implied Equity Value | E22: Implied Share Price
B23: EV / EBITDA Multiple | C23: =C14*C17 -> 1217840.8 | D23: =C23-C20 -> 1384997.9 | E23: =D23/(Assumptions!$C$42*1000) -> 28.556657
B24: EV / Revenue Multiple | C24: =D14*C18 -> 1273975.4 | D24: =C24-C20 -> 1441132.4 | E24: =D24/(Assumptions!$C$42*1000) -> 29.71407
B25: P / E Multiple (direct to equity) | C25: n.a. | D25: n.a. | E25: =E14*C19 -> 25.41998
B27: Exit Multiple Valuation (Alternative Terminal Value)
B28: Exit EV / EBITDA Multiple (= Median Comp) | C28: =C14 -> 11.5
B29: FY2030E EBITDA ($000s) | C29: ='Income Statement'!L12 -> 140483.03
B30: Terminal Value (Exit Multiple) | C30: =C28*C29 -> 1615554.9
B31: PV of Terminal Value | C31: =C30*'DCF Valuation'!L15 -> 1005254.6
B32: Enterprise Value (Exit Multiple Method) | C32: ='DCF Valuation'!C19+C31 -> 1301432.9
B33: Implied Equity Value | C33: =C32-C20 -> 1468590
B34: Implied Share Price ($) | C34: =C33/(Assumptions!$C$42*1000) -> 30.280206
B36: Valuation Summary — DCF vs. Comparables, Side by Side
B37: Methodology | C37: Low | D37: High | E37: Point Estimate
B38: DCF — Perpetuity Growth | C38: =MIN(Sensitivity!D9:H13) -> 21.167602 | D38: =MAX(Sensitivity!D9:H13) -> 32.17867 | E38: ='DCF Valuation'!C28 -> 25.247626
B39: DCF — Exit Multiple (±1.0x) | C39: =('DCF Valuation'!C19+(C28-1)*C29*'DCF Valuation'!L15-C20)/(Assumptions!$C$42*1000) -> 28.477867 | D39: =('DCF Valuation'!C19+(C28+1)*C29*'DCF Valuation'!L15-C20)/(Assumptions!$C$42*1000) -> 32.082545 | E39: =C34 -> 30.280206
B40: Comps — EV/EBITDA (range) | C40: =(MIN(C8:C12)*C17-C20)/(Assumptions!$C$42*1000) -> 24.189679 | D40: =(MAX(C8:C12)*C17-C20)/(Assumptions!$C$42*1000) -> 31.83189 | E40: =E23 -> 28.556657
B41: Comps — EV/Revenue (range) | C41: =(MIN(D8:D12)*C18-C20)/(Assumptions!$C$42*1000) -> 23.147187 | D41: =(MAX(D8:D12)*C18-C20)/(Assumptions!$C$42*1000) -> 34.639233 | E41: =E24 -> 29.71407
B42: Comps — P/E (range) | C42: =MIN(E8:E12)*C19 -> 21.435226 | D42: =MAX(E8:E12)*C19 -> 28.168086 | E42: =E25 -> 25.41998
B43: Implied Valuation Range (All Methods) | C43: =MIN(C38:C42) -> 21.167602 | D43: =MAX(D38:D42) -> 34.639233 | E43: =AVERAGE(E38:E42) -> 27.843708
C44: DCF - Perpetuity | D44: DCF - Exit Mult. | E44: Comps - EV/EBITDA | F44: Comps - EV/Rev | G44: Comps - P/E
B45: (chart helper) base = Low | C45: =C38 -> 21.167602 | D45: =C39 -> 28.477867 | E45: =C40 -> 24.189679 | F45: =C41 -> 23.147187 | G45: =C42 -> 21.435226
B46: (chart helper) span = High - Low | C46: =D38-C38 -> 11.011069 | D46: =D39-C39 -> 3.604678 | E46: =D40-C40 -> 7.6422105 | F46: =D41-C41 -> 11.492046 | G46: =D42-C42 -> 6.7328596

Sheet Sensitivity
B1: SENSITIVITY ANALYSIS — IMPLIED SHARE PRICE
B3: ■ Blue = Input ■ Black = Formula ■ Green = Link to Another Sheet
B6: Two-Way Data Table: WACC (rows) × Terminal Growth Rate (columns)
B8: WACC \ Terminal Growth | D8: =Assumptions!$C$41+(-0.01) -> 0.013 | E8: =Assumptions!$C$41+(-0.005) -> 0.018 | F8: =Assumptions!$C$41+(0) -> 0.023 | G8: =Assumptions!$C$41+(0.005) -> 0.028 | H8: =Assumptions!$C$41+(0.01) -> 0.033
C9: =Assumptions!$C$40+(-0.01) -> 0.089535182 | D9: =(('DCF Valuation'!H13/(1+$C9)^1+'DCF Valuation'!I13/(1+$C9)^2+'DCF Valuation'!J13/(1+$C9)^3+'DCF Valuation'!K13/(1+$C9)^4+'DCF Valuation'!L13/(1+$C9)^5)+(('DCF Valuation'!L13*(1+D$8))/($C9-D$8)/(1+$C9)^5)-'DCF Valuation'!$C$25)/('DCF Valuation'!$C$27*1000) -> 25.989126 | E9: =(('DCF Valuation'!H13/(1+$C9)^1+'DCF Valuation'!I13/(1+$C9)^2+'DCF Valuation'!J13/(1+$C9)^3+'DCF Valuation'!K13/(1+$C9)^4+'DCF Valuation'!L13/(1+$C9)^5)+(('DCF Valuation'!L13*(1+E$8))/($C9-E$8)/(1+$C9)^5)-'DCF Valuation'!$C$25)/('DCF Valuation'!$C$27*1000) -> 27.212045 | F9: =(('DCF Valuation'!H13/(1+$C9)^1+'DCF Valuation'!I13/(1+$C9)^2+'DCF Valuation'!J13/(1+$C9)^3+'DCF Valuation'!K13/(1+$C9)^4+'DCF Valuation'!L13/(1+$C9)^5)+(('DCF Valuation'!L13*(1+F$8))/($C9-F$8)/(1+$C9)^5)-'DCF Valuation'!$C$25)/('DCF Valuation'!$C$27*1000) -> 28.618765 | G9: =(('DCF Valuation'!H13/(1+$C9)^1+'DCF Valuation'!I13/(1+$C9)^2+'DCF Valuation'!J13/(1+$C9)^3+'DCF Valuation'!K13/(1+$C9)^4+'DCF Valuation'!L13/(1+$C9)^5)+(('DCF Valuation'!L13*(1+G$8))/($C9-G$8)/(1+$C9)^5)-'DCF Valuation'!$C$25)/('DCF Valuation'!$C$27*1000) -> 30.254089 | H9: =(('DCF Valuation'!H13/(1+$C9)^1+'DCF Valuation'!I13/(1+$C9)^2+'DCF Valuation'!J13/(1+$C9)^3+'DCF Valuation'!K13/(1+$C9)^4+'DCF Valuation'!L13/(1+$C9)^5)+(('DCF Valuation'!L13*(1+H$8))/($C9-H$8)/(1+$C9)^5)-'DCF Valuation'!$C$25)/('DCF Valuation'!$C$27*1000) -> 32.17867
C10: =Assumptions!$C$40+(-0.005) -> 0.094535182 | D10: =(('DCF Valuation'!H13/(1+$C10)^1+'DCF Valuation'!I13/(1+$C10)^2+'DCF Valuation'!J13/(1+$C10)^3+'DCF Valuation'!K13/(1+$C10)^4+'DCF Valuation'!L13/(1+$C10)^5)+(('DCF Valuation'!L13*(1+D$8))/($C10-D$8)/(1+$C10)^5)-'DCF Valuation'!$C$25)/('DCF Valuation'!$C$27*1000) -> 24.560812 | E10: =(('DCF Valuation'!H13/(1+$C10)^1+'DCF Valuation'!I13/(1+$C10)^2+'DCF Valuation'!J13/(1+$C10)^3+'DCF Valuation'!K13/(1+$C10)^4+'DCF Valuation'!L13/(1+$C10)^5)+(('DCF Valuation'!L13*(1+E$8))/($C10-E$8)/(1+$C10)^5)-'DCF Valuation'!$C$25)/('DCF Valuation'!$C$27*1000) -> 25.614273 | F10: =(('DCF Valuation'!H13/(1+$C10)^1+'DCF Valuation'!I13/(1+$C10)^2+'DCF Valuation'!J13/(1+$C10)^3+'DCF Valuation'!K13/(1+$C10)^4+'DCF Valuation'!L13/(1+$C10)^5)+(('DCF Valuation'!L13*(1+F$8))/($C10-F$8)/(1+$C10)^5)-'DCF Valuation'!$C$25)/('DCF Valuation'!$C$27*1000) -> 26.814999 | G10: =(('DCF Valuation'!H13/(1+$C10)^1+'DCF Valuation'!I13/(1+$C10)^2+'DCF Valuation'!J13/(1+$C10)^3+'DCF Valuation'!K13/(1+$C10)^4+'DCF Valuation'!L13/(1+$C10)^5)+(('DCF Valuation'!L13*(1+G$8))/($C10-G$8)/(1+$C10)^5)-'DCF Valuation'!$C$25)/('DCF Valuation'!$C$27*1000) -> 28.19619 | H10: =(('DCF Valuation'!H13/(1+$C10)^1+'DCF Valuation'!I13/(1+$C10)^2+'DCF Valuation'!J13/(1+$C10)^3+'DCF Valuation'!K13/(1+$C10)^4+'DCF Valuation'!L13/(1+$C10)^5)+(('DCF Valuation'!L13*(1+H$8))/($C10-H$8)/(1+$C10)^5)-'DCF Valuation'!$C$25)/('DCF Valuation'!$C$27*1000) -> 29.801836
C11: =Assumptions!$C$40+(0) -> 0.099535182 | D11: =(('DCF Valuation'!H13/(1+$C11)^1+'DCF Valuation'!I13/(1+$C11)^2+'DCF Valuation'!J13/(1+$C11)^3+'DCF Valuation'!K13/(1+$C11)^4+'DCF Valuation'!L13/(1+$C11)^5)+(('DCF Valuation'!L13*(1+D$8))/($C11-D$8)/(1+$C11)^5)-'DCF Valuation'!$C$25)/('DCF Valuation'!$C$27*1000) -> 23.298306 | E11: =(('DCF Valuation'!H13/(1+$C11)^1+'DCF Valuation'!I13/(1+$C11)^2+'DCF Valuation'!J13/(1+$C11)^3+'DCF Valuation'!K13/(1+$C11)^4+'DCF Valuation'!L13/(1+$C11)^5)+(('DCF Valuation'!L13*(1+E$8))/($C11-E$8)/(1+$C11)^5)-'DCF Valuation'!$C$25)/('DCF Valuation'!$C$27*1000) -> 24.213197 | F11: =(('DCF Valuation'!H13/(1+$C11)^1+'DCF Valuation'!I13/(1+$C11)^2+'DCF Valuation'!J13/(1+$C11)^3+'DCF Valuation'!K13/(1+$C11)^4+'DCF Valuation'!L13/(1+$C11)^5)+(('DCF Valuation'!L13*(1+F$8))/($C11-F$8)/(1+$C11)^5)-'DCF Valuation'!$C$25)/('DCF Valuation'!$C$27*1000) -> 25.247626 | G11: =(('DCF Valuation'!H13/(1+$C11)^1+'DCF Valuation'!I13/(1+$C11)^2+'DCF Valuation'!J13/(1+$C11)^3+'DCF Valuation'!K13/(1+$C11)^4+'DCF Valuation'!L13/(1+$C11)^5)+(('DCF Valuation'!L13*(1+G$8))/($C11-G$8)/(1+$C11)^5)-'DCF Valuation'!$C$25)/('DCF Valuation'!$C$27*1000) -> 26.42666 | H11: =(('DCF Valuation'!H13/(1+$C11)^1+'DCF Valuation'!I13/(1+$C11)^2+'DCF Valuation'!J13/(1+$C11)^3+'DCF Valuation'!K13/(1+$C11)^4+'DCF Valuation'!L13/(1+$C11)^5)+(('DCF Valuation'!L13*(1+H$8))/($C11-H$8)/(1+$C11)^5)-'DCF Valuation'!$C$25)/('DCF Valuation'!$C$27*1000) -> 27.782899
C12: =Assumptions!$C$40+(0.005) -> 0.10453518 | D12: =(('DCF Valuation'!H13/(1+$C12)^1+'DCF Valuation'!I13/(1+$C12)^2+'DCF Valuation'!J13/(1+$C12)^3+'DCF Valuation'!K13/(1+$C12)^4+'DCF Valuation'!L13/(1+$C12)^5)+(('DCF Valuation'!L13*(1+D$8))/($C12-D$8)/(1+$C12)^5)-'DCF Valuation'!$C$25)/('DCF Valuation'!$C$27*1000) -> 22.174421 | E12: =(('DCF Valuation'!H13/(1+$C12)^1+'DCF Valuation'!I13/(1+$C12)^2+'DCF Valuation'!J13/(1+$C12)^3+'DCF Valuation'!K13/(1+$C12)^4+'DCF Valuation'!L13/(1+$C12)^5)+(('DCF Valuation'!L13*(1+E$8))/($C12-E$8)/(1+$C12)^5)-'DCF Valuation'!$C$25)/('DCF Valuation'!$C$27*1000) -> 22.974706 | F12: =(('DCF Valuation'!H13/(1+$C12)^1+'DCF Valuation'!I13/(1+$C12)^2+'DCF Valuation'!J13/(1+$C12)^3+'DCF Valuation'!K13/(1+$C12)^4+'DCF Valuation'!L13/(1+$C12)^5)+(('DCF Valuation'!L13*(1+F$8))/($C12-F$8)/(1+$C12)^5)-'DCF Valuation'!$C$25)/('DCF Valuation'!$C$27*1000) -> 23.873143 | G12: =(('DCF Valuation'!H13/(1+$C12)^1+'DCF Valuation'!I13/(1+$C12)^2+'DCF Valuation'!J13/(1+$C12)^3+'DCF Valuation'!K13/(1+$C12)^4+'DCF Valuation'!L13/(1+$C12)^5)+(('DCF Valuation'!L13*(1+G$8))/($C12-G$8)/(1+$C12)^5)-'DCF Valuation'!$C$25)/('DCF Valuation'!$C$27*1000) -> 24.888968 | H12: =(('DCF Valuation'!H13/(1+$C12)^1+'DCF Valuation'!I13/(1+$C12)^2+'DCF Valuation'!J13/(1+$C12)^3+'DCF Valuation'!K13/(1+$C12)^4+'DCF Valuation'!L13/(1+$C12)^5)+(('DCF Valuation'!L13*(1+H$8))/($C12-H$8)/(1+$C12)^5)-'DCF Valuation'!$C$25)/('DCF Valuation'!$C$27*1000) -> 26.046798
C13: =Assumptions!$C$40+(0.01) -> 0.10953518 | D13: =(('DCF Valuation'!H13/(1+$C13)^1+'DCF Valuation'!I13/(1+$C13)^2+'DCF Valuation'!J13/(1+$C13)^3+'DCF Valuation'!K13/(1+$C13)^4+'DCF Valuation'!L13/(1+$C13)^5)+(('DCF Valuation'!L13*(1+D$8))/($C13-D$8)/(1+$C13)^5)-'DCF Valuation'!$C$25)/('DCF Valuation'!$C$27*1000) -> 21.167602 | E13: =(('DCF Valuation'!H13/(1+$C13)^1+'DCF Valuation'!I13/(1+$C13)^2+'DCF Valuation'!J13/(1+$C13)^3+'DCF Valuation'!K13/(1+$C13)^4+'DCF Valuation'!L13/(1+$C13)^5)+(('DCF Valuation'!L13*(1+E$8))/($C13-E$8)/(1+$C13)^5)-'DCF Valuation'!$C$25)/('DCF Valuation'!$C$27*1000) -> 21.872142 | F13: =(('DCF Valuation'!H13/(1+$C13)^1+'DCF Valuation'!I13/(1+$C13)^2+'DCF Valuation'!J13/(1+$C13)^3+'DCF Valuation'!K13/(1+$C13)^4+'DCF Valuation'!L13/(1+$C13)^5)+(('DCF Valuation'!L13*(1+F$8))/($C13-F$8)/(1+$C13)^5)-'DCF Valuation'!$C$25)/('DCF Valuation'!$C$27*1000) -> 22.658098 | G13: =(('DCF Valuation'!H13/(1+$C13)^1+'DCF Valuation'!I13/(1+$C13)^2+'DCF Valuation'!J13/(1+$C13)^3+'DCF Valuation'!K13/(1+$C13)^4+'DCF Valuation'!L13/(1+$C13)^5)+(('DCF Valuation'!L13*(1+G$8))/($C13-G$8)/(1+$C13)^5)-'DCF Valuation'!$C$25)/('DCF Valuation'!$C$27*1000) -> 23.540449 | H13: =(('DCF Valuation'!H13/(1+$C13)^1+'DCF Valuation'!I13/(1+$C13)^2+'DCF Valuation'!J13/(1+$C13)^3+'DCF Valuation'!K13/(1+$C13)^4+'DCF Valuation'!L13/(1+$C13)^5)+(('DCF Valuation'!L13*(1+H$8))/($C13-H$8)/(1+$C13)^5)-'DCF Valuation'!$C$25)/('DCF Valuation'!$C$27*1000) -> 24.538088
B16: Base case (center cell, gold) matches the DCF Valuation tab's implied share price.
B17: Each cell independently recomputes Enterprise → Equity Value → Share Price for its WACC/g pair.

Sheet Econometrics
B1: ECONOMETRICS & REGRESSION LAB
B4: ■ Blue = Input ■ Black = Formula ■ Green = Link to Another Sheet
B6: CAPM Beta Estimation — 36-Month Return Series
B7: Month # | C7: Stock Return (%) | D7: Market Return (%) | F7: Regression Output: Stock Return ~ Market Return
B8: 1 | C8: 0.019042771 | D8: -0.00048406483 | F8: Beta (Slope) | H8: =SLOPE(C8:C43,D8:D43) -> 1.3085269
B9: 2 | C9: -0.035181854 | D9: -0.001780662
B10: 3 | C10: 0.025865524 | D10: 0.00099078623 | F10: Alpha (Intercept) | H10: =INTERCEPT(C8:C43,D8:D43) -> 0.0060557781
B11: 4 | C11: 0.016165979 | D11: 0.037589268
B12: 5 | C12: -0.0011175214 | D12: 0.00025852723 | F12: R-Squared | H12: =RSQ(C8:C43,D8:D43) -> 0.79337671
B13: 6 | C13: -0.077817233 | D13: -0.061380904
B14: 7 | C14: 0.02830123 | D14: 0.020954325 | F14: Correlation (r) | H14: =CORREL(C8:C43,D8:D43) -> 0.89071697
B15: 8 | C15: 0.016987102 | D15: -0.0060301865
B16: 9 | C16: 0.014547974 | D16: -0.0037631408 | F16: Std. Error of Beta | H16: =STEYX(C8:C43,D8:D43)/STDEV(D8:D43)/SQRT(COUNT(D8:D43)-1) -> 0.1145231
B17: 10 | C17: 0.023693821 | D17: 0.011214815
B18: 11 | C18: 0.038119955 | D18: 0.016453398 | F18: Observations (n) | H18: =COUNT(D8:D43) -> 36
B19: 12 | C19: 0.081511939 | D19: 0.058360141
B20: 13 | C20: 0.024325346 | D20: 0.035548643
B21: 14 | C21: -0.0064676442 | D21: 0.010972823 | F21: t-Statistic (Beta = 0) | H21: =H8/H12 -> 1.6493134
B22: 15 | C22: -0.043467255 | D22: -0.027224472 | F22: Statistically significant at 5% if |t| > 2.03 (df=34)
B23: 16 | C23: -0.030627638 | D23: -0.039659807
B24: 17 | C24: 0.013644973 | D24: 0.017085399
B25: 18 | C25: 0.14114955 | D25: 0.064998637
B26: 19 | C26: -0.012884448 | D26: 0.0078745589
B27: 20 | C27: -0.028370719 | D27: 0.0012154518
B28: 21 | C28: 0.056936678 | D28: 0.02992993
B29: 22 | C29: -0.02750917 | D29: -0.059409538
B30: 23 | C30: 0.0058990442 | D30: -0.0080524793
B31: 24 | C31: 0.056679147 | D31: 0.028066314
B32: 25 | C32: 0.093036336 | D32: 0.045303197
B33: 26 | C33: -0.0071853549 | D33: -0.0048283353
B34: 27 | C34: -0.012453807 | D34: 0.022946994
... B43: 36 | C43: 0.11823307 | D43: 0.045420551
B46: Macro Regression — Revenue Growth Sensitivity to GDP Growth
B47: Independent variable: Real GDP Growth (%), FY2022–FY2025 (Assumptions!D7:G7)
B48: Segment | C48: GDP Beta (Slope) | D48: Intercept | E48: R² | F48: Correlation
B49: Heritage Textiles | C49: =SLOPE(Assumptions!D20:G20,Assumptions!D7:G7) -> -0.61967976 | D49: =INTERCEPT(Assumptions!D20:G20,Assumptions!D7:G7) -> 0.05965097 | E49: =RSQ(Assumptions!D20:G20,Assumptions!D7:G7) -> 0.071974236 | F49: =CORREL(Assumptions!D20:G20,Assumptions!D7:G7) -> -0.26828015
B50: Private Wealth Advisory | C50: =SLOPE(Assumptions!D21:G21,Assumptions!D7:G7) -> 2.1397257 | D50: =INTERCEPT(Assumptions!D21:G21,Assumptions!D7:G7) -> 0.088378676 | E50: =RSQ(Assumptions!D21:G21,Assumptions!D7:G7) -> 0.27167566 | F50: =CORREL(Assumptions!D21:G21,Assumptions!D7:G7) -> 0.52122515
B51: Fine Estates (Real Assets) | C51: =SLOPE(Assumptions!D22:G22,Assumptions!D7:G7) -> 2.0797774 | D51: =INTERCEPT(Assumptions!D22:G22,Assumptions!D7:G7) -> 0.036448982 | E51: =RSQ(Assumptions!D22:G22,Assumptions!D7:G7) -> 0.11110423 | F51: =CORREL(Assumptions!D22:G22,Assumptions!D7:G7) -> 0.33332302
B52: Total Revenue | C52: =SLOPE('Revenue Build'!D23:G23,Assumptions!D7:G7) -> 1.1066725 | D52: =INTERCEPT('Revenue Build'!D23:G23,Assumptions!D7:G7) -> 0.05941082 | E52: =RSQ('Revenue Build'!D23:G23,Assumptions!D7:G7) -> 0.12333936 | F52: =CORREL('Revenue Build'!D23:G23,Assumptions!D7:G7) -> 0.35119705
B54: Segment Growth Correlation Matrix (FY2022–FY2025)
C55: Heritage Textiles | D55: Private Wealth Advisory | E55: Fine Estates
B56: Heritage Textiles | C56: =CORREL(Assumptions!D20:G20,Assumptions!D20:G20) -> 1 | D56: =CORREL(Assumptions!D20:G20,Assumptions!D21:G21) -> 0.65961876 | E56: =CORREL(Assumptions!D20:G20,Assumptions!D22:G22) -> 0.20898201
B57: Private Wealth Advisory | C57: =CORREL(Assumptions!D21:G21,Assumptions!D20:G20) -> 0.65961876 | D57: =CORREL(Assumptions!D21:G21,Assumptions!D21:G21) -> 1 | E57: =CORREL(Assumptions!D21:G21,Assumptions!D22:G22) -> 0.60807094
B58: Fine Estates | C58: =CORREL(Assumptions!D22:G22,Assumptions!D20:G20) -> 0.20898201 | D58: =CORREL(Assumptions!D22:G22,Assumptions!D21:G21) -> 0.60807094 | E58: =CORREL(Assumptions!D22:G22,Assumptions!D22:G22) -> 1

Sheet Checks
B1: MODEL INTEGRITY CHECKS
B3: ■ Blue = Input ■ Black = Formula ■ Green = Link to Another Sheet
B6: Overall Status | C6: =IF(COUNTIF(C8:C26,"*FAIL*")=0,"✅ ALL CHECKS PASSED","❌ REVIEW REQUIRED") -> ✅ ALL CHECKS PASSED
B8: Assets = Liabilities + Equity | C8: =IF(SUMPRODUCT(--(ABS('Balance Sheet'!C22:L22)>0.01))=0,"✅ PASS","❌ FAIL") -> ✅ PASS | D8: Balance Sheet's Balance Check row (Assets − Liab&Equity) is tested for all 10 years; must equal zero (within $0.01) every year.
B10: Cash Flow Reconciles to Balance Sheet | C10: =IF(SUMPRODUCT(--(ABS('Cash Flow'!D25:L25-'Balance Sheet'!D7:L7)>0.01))=0,"✅ PASS","❌ FAIL") -> ✅ PASS | D10: Ending Cash on the Cash Flow Statement is tested against the Cash balance carried on the Balance Sheet for FY2022–FY2030.
B12: Net Income Linked Correctly | C12: =IF(AND(SUMPRODUCT(--(ABS('Income Statement'!D22:L22-'Cash Flow'!D7:L7)>0.01))=0,SUMPRODUCT(--(ABS(('Balance Sheet'!D19:L19-'Balance Sheet'!C19:K19)-'Income Statement'!D22:L22)>0.01))=0),"✅ PASS","❌ FAIL") -> ✅ PASS | D12: Confirms Net Income flows identically from the Income Statement into the Cash Flow Statement, and that Retained Earnings rolls forward by exactly Net Income each year (no dividends/plugs).
B14: No Formula Errors (REF, DIV-by-zero, N/A, etc.) | C14: =IF((SUMPRODUCT(--ISERROR('Income Statement'!C6:L26))+SUMPRODUCT(--ISERROR('Balance Sheet'!C6:L22))+SUMPRODUCT(--ISERROR('Cash Flow'!C6:L25))+SUMPRODUCT(--ISERROR('DCF Valuation'!C6:L28))+SUMPRODUCT(--ISERROR('Revenue Build'!C6:L28))+SUMPRODUCT(--ISERROR(Assumptions!C6:L46))+SUMPRODUCT(--ISERROR(Sensitivity!C6:J17))+SUMPRODUCT(--ISERROR(Econometrics!C6:N60))+SUMPRODUCT(--ISERROR('Working Capital'!C6:L18))+SUMPRODUCT(--ISERROR('Debt Schedule'!C6:L15))+SUMPRODUCT(--ISERROR(Comparables!C6:H70)))=0,"✅ PASS","❌ FAIL") -> ✅ PASS | D14: Scans every statement, the revenue build, assumptions, sensitivity grid, and econometrics lab for any error-valued cell.
B16: Circular References = 0 (Design Confirmation) | C16: ="ℹ️ VERIFIED BY DESIGN" -> ℹ️ VERIFIED BY DESIGN | D16: Unlike the other rows on this sheet, this is not a live formula test — no worksheet formula can detect circularity. It is manually confirmed: debt is a scheduled roll-forward (opening + new borrowings − repayments, each a manual input) rather than a cash-sweep revolver, so ending debt and interest expense never depend on the cash flow they help produce. You can independently verify this via Excel's Formulas > Error Checking > Circular References menu (will report none), with iterative calculation OFF.
B18: Segment Revenue Ties to Total | C18: =IF(SUMPRODUCT(--(ABS('Revenue Build'!C22:L22-('Revenue Build'!C9:L9+'Revenue Build'!C14:L14+'Revenue Build'!C19:L19))>0.01))=0,"✅ PASS","❌ FAIL") -> ✅ PASS | D18: Heritage Textiles + Private Wealth Advisory + Fine Estates revenue sums to Total Revenue for all 10 years.
B20: Units × ASP = Segment Revenue | C20: =IF(SUMPRODUCT(--(ABS('Revenue Build'!C9:L9-'Revenue Build'!C7:L7*'Revenue Build'!C8:L8)>0.01))=0,"✅ PASS","❌ FAIL") -> ✅ PASS | D20: Heritage Textiles Revenue independently recomputed as Units Sold × Average Selling Price and compared to the reported Revenue line.
B22: Sensitivity Base Case Matches DCF | C22: =IF(ABS('DCF Valuation'!C28-Sensitivity!F11)<0.01,"✅ PASS","❌ FAIL") -> ✅ PASS | D22: The center cell of the WACC × Terminal Growth sensitivity grid (Sensitivity!F11) is cross-checked against the DCF tab's Implied Share Price.
B24: Debt Schedule Ties to Balance Sheet | C24: =IF(SUMPRODUCT(--(ABS('Debt Schedule'!C10:L10-'Balance Sheet'!C16:L16)>0.01))=0,"✅ PASS","❌ FAIL") -> ✅ PASS | D24: Ending Debt Balance on the Debt Schedule is tested against the Long-Term Debt line carried on the Balance Sheet for all 10 years.
B26: Working Capital Schedule Ties to Balance Sheet | C26: =IF(AND(SUMPRODUCT(--(ABS('Working Capital'!C12:L12-'Balance Sheet'!C8:L8)>0.01))=0,SUMPRODUCT(--(ABS('Working Capital'!C13:L13-'Balance Sheet'!C9:L9)>0.01))=0,SUMPRODUCT(--(ABS('Working Capital'!C14:L14-'Balance Sheet'!C15:L15)>0.01))=0),"✅ PASS","❌ FAIL") -> ✅ PASS | D26: Accounts Receivable, Inventory, and Accounts Payable on the Working Capital schedule (DSO/DIO/DPO-driven) are tested against the corresponding Balance Sheet lines.
